{"2020-04-18T15:45:00.000Z":{"dymclFPd Zone Temperature":71.5749969482,"ygZXCNrx Humidifier Valve %":0,"dECNkkkx Duct Static Pressure":0.5,"JJTf4KIN Mixed Air Temperature":68.4000015259,"ejzJNJVA TvG2WGjE Flow Setpoint":750,"QaxazYRs Pre Heating Temp":66.2249984741,"ymhl1rIT Static Pressure Setpoint":0.5,"7J5Znp6z Preheat Valve %":0,"m99GC7uz Supply Fan Output %":12.1901092529,"3p3Wd2Zp Cooling Valve %":0,"nqWMaKsU hq1bHbcu Flow":1.4885225296,"iAtum58lYXB6Es Zone Relative Humidity %":38.8250007629,"AqlRfdQi Power (Calc)":0.0290608738,"9tAKv3tG Setpoint Temperature":58,"L4Vb3H0J Schedule":null,"Kamr4cZz Supply Air Temperature":63.25,"QNupgV5D Supply Relative Humidity Setpoint %":30,"OratacDL Supply Relative Humidity %":49.1500015259,"b1eBcHjc Return Air Temperature":73.3000030518,"type":"AHU","subType":"","Status":true},"2020-04-18T16:00:00.000Z":{"dymclFPd Zone Temperature":71.5500030518,"ygZXCNrx Humidifier Valve %":0,"dECNkkkx Duct Static Pressure":0.5,"JJTf4KIN Mixed Air Temperature":68.1999969482,"ejzJNJVA TvG2WGjE Flow Setpoint":750,"QaxazYRs Pre Heating Temp":66.0749969482,"ymhl1rIT Static Pressure Setpoint":0.5,"7J5Znp6z Preheat Valve %":0,"m99GC7uz Supply Fan Output %":12.1920137405,"3p3Wd2Zp Cooling Valve %":0,"nqWMaKsU hq1bHbcu Flow":1.3343721628,"iAtum58lYXB6Es Zone Relative Humidity %":39.0250015259,"AqlRfdQi Power (Calc)":0.0290744967,"9tAKv3tG Setpoint Temperature":58,"L4Vb3H0J Schedule":null,"Kamr4cZz Supply Air Temperature":63.2750015259,"QNupgV5D Supply Relative Humidity Setpoint %":30,"OratacDL Supply Relative Humidity %":49.2000007629,"b1eBcHjc Return Air Temperature":73.3000030518,"type":"AHU","subType":"","Status":true},"2020-04-18T16:15:00.000Z":{"dymclFPd Zone Temperature":71.5749969482,"ygZXCNrx Humidifier Valve %":0,"dECNkkkx Duct Static Pressure":0.5,"JJTf4KIN Mixed Air Temperature":68.4250030518,"ejzJNJVA TvG2WGjE Flow Setpoint":750,"QaxazYRs Pre Heating Temp":66.1750030518,"ymhl1rIT Static Pressure Setpoint":0.5,"7J5Znp6z Preheat Valve %":0,"m99GC7uz Supply Fan Output %":12.1974430084,"3p3Wd2Zp Cooling Valve %":0,"nqWMaKsU hq1bHbcu Flow":1.3866958618,"iAtum58lYXB6Es Zone Relative Humidity %":39.0750007629,"AqlRfdQi Power (Calc)":0.0291133558,"9tAKv3tG Setpoint Temperature":58,"L4Vb3H0J Schedule":null,"Kamr4cZz Supply Air Temperature":63.2750015259,"QNupgV5D Supply Relative Humidity Setpoint %":30,"OratacDL Supply Relative Humidity %":49.25,"b1eBcHjc Return Air Temperature":73.3499984741,"type":"AHU","subType":"","Status":true},"2020-04-18T16:30:00.000Z":{"dymclFPd Zone Temperature":71.5999984741,"ygZXCNrx Humidifier Valve %":0,"dECNkkkx Duct Static Pressure":0.5,"JJTf4KIN Mixed Air Temperature":68.3000030518,"ejzJNJVA TvG2WGjE Flow Setpoint":750,"QaxazYRs Pre Heating Temp":66.1999969482,"ymhl1rIT Static Pressure Setpoint":0.5,"7J5Znp6z Preheat Valve %":0,"m99GC7uz Supply Fan Output %":12.2024230957,"3p3Wd2Zp Cooling Valve %":0,"nqWMaKsU hq1bHbcu Flow":1.4772181511,"iAtum58lYXB6Es Zone Relative Humidity %":39.125,"AqlRfdQi Power (Calc)":0.0291490303,"9tAKv3tG Setpoint Temperature":58,"L4Vb3H0J Schedule":null,"Kamr4cZz Supply Air Temperature":63.3250007629,"QNupgV5D Supply Relative Humidity Setpoint %":30,"OratacDL Supply Relative Humidity %":49.1749992371,"b1eBcHjc Return Air Temperature":73.3499984741,"type":"AHU","subType":"","Status":true},"2020-04-18T16:45:00.000Z":{"dymclFPd Zone Temperature":71.5999984741,"ygZXCNrx Humidifier Valve %":0,"dECNkkkx Duct Static Pressure":0.5,"JJTf4KIN Mixed Air Temperature":68.4250030518,"ejzJNJVA TvG2WGjE Flow Setpoint":750,"QaxazYRs Pre Heating Temp":66.0749969482,"ymhl1rIT Static Pressure Setpoint":0.5,"7J5Znp6z Preheat Valve %":0,"m99GC7uz Supply Fan Output %":12.1976728439,"3p3Wd2Zp Cooling Valve %":0,"nqWMaKsU hq1bHbcu Flow":1.436144352,"iAtum58lYXB6Es Zone Relative Humidity %":39.1500015259,"AqlRfdQi Power (Calc)":0.0291150015,"9tAKv3tG Setpoint Temperature":58,"L4Vb3H0J Schedule":null,"Kamr4cZz Supply Air Temperature":63.1749992371,"QNupgV5D Supply Relative Humidity Setpoint %":30,"OratacDL Supply Relative Humidity %":49.4749984741,"b1eBcHjc Return Air Temperature":73.4000015259,"type":"AHU","subType":"","Status":true},"2020-04-18T17:00:00.000Z":{"dymclFPd Zone Temperature":71.625,"ygZXCNrx Humidifier Valve %":0,"dECNkkkx Duct Static Pressure":0.5,"JJTf4KIN Mixed Air Temperature":68.0500030518,"ejzJNJVA TvG2WGjE Flow Setpoint":750,"QaxazYRs Pre Heating Temp":66.0,"ymhl1rIT Static Pressure Setpoint":0.5,"7J5Znp6z Preheat Valve %":0,"m99GC7uz Supply Fan Output %":12.1968622208,"3p3Wd2Zp Cooling Valve %":0,"nqWMaKsU hq1bHbcu Flow":1.2588853836,"iAtum58lYXB6Es Zone Relative Humidity %":39.125,"AqlRfdQi Power (Calc)":0.0291091972,"9tAKv3tG Setpoint Temperature":58,"L4Vb3H0J Schedule":null,"Kamr4cZz Supply Air Temperature":63.2000007629,"QNupgV5D Supply Relative Humidity Setpoint %":30,"OratacDL Supply Relative Humidity %":49.4500007629,"b1eBcHjc Return Air Temperature":73.4250030518,"type":"AHU","subType":"","Status":true},"2020-04-18T17:15:00.000Z":{"dymclFPd Zone Temperature":71.625,"ygZXCNrx Humidifier Valve %":0,"dECNkkkx Duct Static Pressure":0.5,"JJTf4KIN Mixed Air Temperature":68.3000030518,"ejzJNJVA TvG2WGjE Flow Setpoint":750,"QaxazYRs Pre Heating Temp":66.0500030518,"ymhl1rIT Static Pressure Setpoint":0.5,"7J5Znp6z Preheat Valve %":0,"m99GC7uz Supply Fan Output %":12.2004137039,"3p3Wd2Zp Cooling Valve %":0,"nqWMaKsU hq1bHbcu Flow":1.4474289417,"iAtum58lYXB6Es Zone Relative Humidity %":39.3499984741,"AqlRfdQi Power (Calc)":0.0291346327,"9tAKv3tG Setpoint Temperature":58,"L4Vb3H0J Schedule":null,"Kamr4cZz Supply Air Temperature":63.2750015259,"QNupgV5D Supply Relative Humidity Setpoint %":30,"OratacDL Supply Relative Humidity %":49.4249992371,"b1eBcHjc Return Air Temperature":73.4749984741,"type":"AHU","subType":"","Status":true},"2020-04-18T17:30:00.000Z":{"dymclFPd Zone Temperature":71.6500015259,"ygZXCNrx Humidifier Valve %":0,"dECNkkkx Duct Static Pressure":0.5,"JJTf4KIN Mixed Air Temperature":68.0749969482,"ejzJNJVA TvG2WGjE Flow Setpoint":750,"QaxazYRs Pre Heating Temp":66.3249969482,"ymhl1rIT Static Pressure Setpoint":0.5,"7J5Znp6z Preheat Valve %":0,"m99GC7uz Supply Fan Output %":12.2044477463,"3p3Wd2Zp Cooling Valve %":0,"nqWMaKsU hq1bHbcu Flow":1.3741445541,"iAtum58lYXB6Es Zone Relative Humidity %":39.0750007629,"AqlRfdQi Power (Calc)":0.0291635421,"9tAKv3tG Setpoint Temperature":58,"L4Vb3H0J Schedule":null,"Kamr4cZz Supply Air Temperature":63.0999984741,"QNupgV5D Supply Relative Humidity Setpoint %":30,"OratacDL Supply Relative Humidity %":49.7249984741,"b1eBcHjc Return Air Temperature":73.5,"type":"AHU","subType":"","Status":true},"2020-04-18T17:45:00.000Z":{"dymclFPd Zone Temperature":71.6750030518,"ygZXCNrx Humidifier Valve %":0,"dECNkkkx Duct Static Pressure":0.5,"JJTf4KIN Mixed Air Temperature":68.1999969482,"ejzJNJVA TvG2WGjE Flow Setpoint":750,"QaxazYRs Pre Heating Temp":65.9250030518,"ymhl1rIT Static Pressure Setpoint":0.5,"7J5Znp6z Preheat Valve %":0,"m99GC7uz Supply Fan Output %":12.1755466461,"3p3Wd2Zp Cooling Valve %":0,"nqWMaKsU hq1bHbcu Flow":1.3579556942,"iAtum58lYXB6Es Zone Relative Humidity %":38.9500007629,"AqlRfdQi Power (Calc)":0.0289568476,"9tAKv3tG Setpoint Temperature":58,"L4Vb3H0J Schedule":null,"Kamr4cZz Supply Air Temperature":61.75,"QNupgV5D Supply Relative Humidity Setpoint %":30,"OratacDL Supply Relative Humidity %":52.125,"b1eBcHjc Return Air Temperature":73.5250015259,"type":"AHU","subType":"","Status":true},"2020-04-18T18:00:00.000Z":{"dymclFPd Zone Temperature":71.6750030518,"ygZXCNrx Humidifier Valve %":0,"dECNkkkx Duct Static Pressure":0.5,"JJTf4KIN Mixed Air Temperature":68.125,"ejzJNJVA TvG2WGjE Flow Setpoint":750,"QaxazYRs Pre Heating Temp":66.0,"ymhl1rIT Static Pressure Setpoint":0.5,"7J5Znp6z Preheat Valve %":0,"m99GC7uz Supply Fan Output %":12.153427124,"3p3Wd2Zp Cooling Valve %":0,"nqWMaKsU hq1bHbcu Flow":1.4301651716,"iAtum58lYXB6Es Zone Relative Humidity %":39.2999992371,"AqlRfdQi Power (Calc)":0.028799315,"9tAKv3tG Setpoint Temperature":58,"L4Vb3H0J Schedule":null,"Kamr4cZz Supply Air Temperature":61.7249984741,"QNupgV5D Supply Relative Humidity Setpoint %":30,"OratacDL Supply Relative Humidity %":52.125,"b1eBcHjc Return Air Temperature":73.5,"type":"AHU","subType":"","Status":true},"2020-04-18T18:15:00.000Z":{"dymclFPd Zone Temperature":71.6750030518,"ygZXCNrx Humidifier Valve %":0,"dECNkkkx Duct Static Pressure":0.5,"JJTf4KIN Mixed Air Temperature":68.6500015259,"ejzJNJVA TvG2WGjE Flow Setpoint":750,"QaxazYRs Pre Heating Temp":66.3000030518,"ymhl1rIT Static Pressure Setpoint":0.5,"7J5Znp6z Preheat Valve %":0,"m99GC7uz Supply Fan Output %":12.1276683807,"3p3Wd2Zp Cooling Valve %":0,"nqWMaKsU hq1bHbcu Flow":1.4321229458,"iAtum58lYXB6Es Zone Relative Humidity %":39.4249992371,"AqlRfdQi Power (Calc)":0.0286165856,"9tAKv3tG Setpoint Temperature":58,"L4Vb3H0J Schedule":null,"Kamr4cZz Supply Air Temperature":61.6500015259,"QNupgV5D Supply Relative Humidity Setpoint %":30,"OratacDL Supply Relative Humidity %":52.2999992371,"b1eBcHjc Return Air Temperature":73.5500030518,"type":"AHU","subType":"","Status":true},"2020-04-18T18:30:00.000Z":{"dymclFPd Zone Temperature":71.6500015259,"ygZXCNrx Humidifier Valve %":0,"dECNkkkx Duct Static Pressure":0.5,"JJTf4KIN Mixed Air Temperature":68.5999984741,"ejzJNJVA TvG2WGjE Flow Setpoint":750,"QaxazYRs Pre Heating Temp":66.25,"ymhl1rIT Static Pressure Setpoint":0.5,"7J5Znp6z Preheat Valve %":0,"m99GC7uz Supply Fan Output %":12.126540184,"3p3Wd2Zp Cooling Valve %":0,"nqWMaKsU hq1bHbcu Flow":1.3396327496,"iAtum58lYXB6Es Zone Relative Humidity %":39.2249984741,"AqlRfdQi Power (Calc)":0.0286086,"9tAKv3tG Setpoint Temperature":58,"L4Vb3H0J Schedule":null,"Kamr4cZz Supply Air Temperature":61.7000007629,"QNupgV5D Supply Relative Humidity Setpoint %":30,"OratacDL Supply Relative Humidity %":52.0999984741,"b1eBcHjc Return Air Temperature":73.5500030518,"type":"AHU","subType":"","Status":true},"2020-04-18T18:45:00.000Z":{"dymclFPd Zone Temperature":71.6750030518,"ygZXCNrx Humidifier Valve %":0,"dECNkkkx Duct Static Pressure":0.5,"JJTf4KIN Mixed Air Temperature":68.3000030518,"ejzJNJVA TvG2WGjE Flow Setpoint":750,"QaxazYRs Pre Heating Temp":65.8249969482,"ymhl1rIT Static Pressure Setpoint":0.5,"7J5Znp6z Preheat Valve %":0,"m99GC7uz Supply Fan Output %":12.1240701675,"3p3Wd2Zp Cooling Valve %":0,"nqWMaKsU hq1bHbcu Flow":1.4005931616,"iAtum58lYXB6Es Zone Relative Humidity %":39.1500015259,"AqlRfdQi Power (Calc)":0.028591122,"9tAKv3tG Setpoint Temperature":58,"L4Vb3H0J Schedule":null,"Kamr4cZz Supply Air Temperature":61.75,"QNupgV5D Supply Relative Humidity Setpoint %":30,"OratacDL Supply Relative Humidity %":52.125,"b1eBcHjc Return Air Temperature":73.5999984741,"type":"AHU","subType":"","Status":true},"2020-04-18T19:00:00.000Z":{"dymclFPd Zone Temperature":71.6750030518,"ygZXCNrx Humidifier Valve %":0,"dECNkkkx Duct Static Pressure":0.5,"JJTf4KIN Mixed Air Temperature":68.2249984741,"ejzJNJVA TvG2WGjE Flow Setpoint":750,"QaxazYRs Pre Heating Temp":66.25,"ymhl1rIT Static Pressure Setpoint":0.5,"7J5Znp6z Preheat Valve %":0,"m99GC7uz Supply Fan Output %":12.1253623962,"3p3Wd2Zp Cooling Valve %":0,"nqWMaKsU hq1bHbcu Flow":1.4478955269,"iAtum58lYXB6Es Zone Relative Humidity %":39.0750007629,"AqlRfdQi Power (Calc)":0.028600265,"9tAKv3tG Setpoint Temperature":58,"L4Vb3H0J Schedule":null,"Kamr4cZz Supply Air Temperature":61.8250007629,"QNupgV5D Supply Relative Humidity Setpoint %":30,"OratacDL Supply Relative Humidity %":52.125,"b1eBcHjc Return Air Temperature":73.5999984741,"type":"AHU","subType":"","Status":true},"2020-04-18T19:15:00.000Z":{"dymclFPd Zone Temperature":71.6750030518,"ygZXCNrx Humidifier Valve %":0,"dECNkkkx Duct Static Pressure":0.5,"JJTf4KIN Mixed Air Temperature":68.4000015259,"ejzJNJVA TvG2WGjE Flow Setpoint":750,"QaxazYRs Pre Heating Temp":66.2249984741,"ymhl1rIT Static Pressure Setpoint":0.5,"7J5Znp6z Preheat Valve %":0,"m99GC7uz Supply Fan Output %":12.1252689362,"3p3Wd2Zp Cooling Valve %":0,"nqWMaKsU hq1bHbcu Flow":1.4603736401,"iAtum58lYXB6Es Zone Relative Humidity %":39.2249984741,"AqlRfdQi Power (Calc)":0.0285996036,"9tAKv3tG Setpoint Temperature":58,"L4Vb3H0J Schedule":null,"Kamr4cZz Supply Air Temperature":61.875,"QNupgV5D Supply Relative Humidity Setpoint %":30,"OratacDL Supply Relative Humidity %":52.0999984741,"b1eBcHjc Return Air Temperature":73.6500015259,"type":"AHU","subType":"","Status":true},"2020-04-18T19:30:00.000Z":{"dymclFPd Zone Temperature":71.6999969482,"ygZXCNrx Humidifier Valve %":0,"dECNkkkx Duct Static Pressure":0.5,"JJTf4KIN Mixed Air Temperature":68.4000015259,"ejzJNJVA TvG2WGjE Flow Setpoint":750,"QaxazYRs Pre Heating Temp":66.0999984741,"ymhl1rIT Static Pressure Setpoint":0.5,"7J5Znp6z Preheat Valve %":0,"m99GC7uz Supply Fan Output %":12.1313085556,"3p3Wd2Zp Cooling Valve %":0,"nqWMaKsU hq1bHbcu Flow":1.3861393929,"iAtum58lYXB6Es Zone Relative Humidity %":39.2000007629,"AqlRfdQi Power (Calc)":0.0286423615,"9tAKv3tG Setpoint Temperature":58,"L4Vb3H0J Schedule":null,"Kamr4cZz Supply Air Temperature":61.9000015259,"QNupgV5D Supply Relative Humidity Setpoint %":30,"OratacDL Supply Relative Humidity %":52.0750007629,"b1eBcHjc Return Air Temperature":73.6999969482,"type":"AHU","subType":"","Status":true},"2020-04-18T19:45:00.000Z":{"dymclFPd Zone Temperature":71.6999969482,"ygZXCNrx Humidifier Valve %":0,"dECNkkkx Duct Static Pressure":0.5,"JJTf4KIN Mixed Air Temperature":68.6500015259,"ejzJNJVA TvG2WGjE Flow Setpoint":750,"QaxazYRs Pre Heating Temp":66.1999969482,"ymhl1rIT Static Pressure Setpoint":0.5,"7J5Znp6z Preheat Valve %":0,"m99GC7uz Supply Fan Output %":12.1197633743,"3p3Wd2Zp Cooling Valve %":0,"nqWMaKsU hq1bHbcu Flow":1.4348984957,"iAtum58lYXB6Es Zone Relative Humidity %":39.3499984741,"AqlRfdQi Power (Calc)":0.0285606638,"9tAKv3tG Setpoint Temperature":58,"L4Vb3H0J Schedule":null,"Kamr4cZz Supply Air Temperature":61.9500007629,"QNupgV5D Supply Relative Humidity Setpoint %":30,"OratacDL Supply Relative Humidity %":52.0499992371,"b1eBcHjc Return Air Temperature":73.6750030518,"type":"AHU","subType":"","Status":true},"2020-04-18T20:00:00.000Z":{"dymclFPd Zone Temperature":71.6999969482,"ygZXCNrx Humidifier Valve %":0,"dECNkkkx Duct Static Pressure":0.5,"JJTf4KIN Mixed Air Temperature":68.2750015259,"ejzJNJVA TvG2WGjE Flow Setpoint":750,"QaxazYRs Pre Heating Temp":66.5,"ymhl1rIT Static Pressure Setpoint":0.5,"7J5Znp6z Preheat Valve %":0,"m99GC7uz Supply Fan Output %":12.1324806213,"3p3Wd2Zp Cooling Valve %":0,"nqWMaKsU hq1bHbcu Flow":1.3923547268,"iAtum58lYXB6Es Zone Relative Humidity %":39.2750015259,"AqlRfdQi Power (Calc)":0.0286506641,"9tAKv3tG Setpoint Temperature":58,"L4Vb3H0J Schedule":null,"Kamr4cZz Supply Air Temperature":61.9749984741,"QNupgV5D Supply Relative Humidity Setpoint %":30,"OratacDL Supply Relative Humidity %":52.0750007629,"b1eBcHjc Return Air Temperature":73.75,"type":"AHU","subType":"","Status":true},"2020-04-18T20:15:00.000Z":{"dymclFPd Zone Temperature":71.6999969482,"ygZXCNrx Humidifier Valve %":0,"dECNkkkx Duct Static Pressure":0.5,"JJTf4KIN Mixed Air Temperature":68.9749984741,"ejzJNJVA TvG2WGjE Flow Setpoint":750,"QaxazYRs Pre Heating Temp":66.375,"ymhl1rIT Static Pressure Setpoint":0.5,"7J5Znp6z Preheat Valve %":0,"m99GC7uz Supply Fan Output %":12.1231889725,"3p3Wd2Zp Cooling Valve %":0,"nqWMaKsU hq1bHbcu Flow":1.3466212749,"iAtum58lYXB6Es Zone Relative Humidity %":39.25,"AqlRfdQi Power (Calc)":0.0285848883,"9tAKv3tG Setpoint Temperature":58,"L4Vb3H0J Schedule":null,"Kamr4cZz Supply Air Temperature":62.0750007629,"QNupgV5D Supply Relative Humidity Setpoint %":30,"OratacDL Supply Relative Humidity %":51.9249992371,"b1eBcHjc Return Air Temperature":73.8000030518,"type":"AHU","subType":"","Status":true},"2020-04-18T20:30:00.000Z":{"dymclFPd Zone Temperature":71.6999969482,"ygZXCNrx Humidifier Valve %":0,"dECNkkkx Duct Static Pressure":0.5,"JJTf4KIN Mixed Air Temperature":68.5749969482,"ejzJNJVA TvG2WGjE Flow Setpoint":750,"QaxazYRs Pre Heating Temp":66.125,"ymhl1rIT Static Pressure Setpoint":0.5,"7J5Znp6z Preheat Valve %":0,"m99GC7uz Supply Fan Output %":12.1483249664,"3p3Wd2Zp Cooling Valve %":0,"nqWMaKsU hq1bHbcu Flow":1.3237874508,"iAtum58lYXB6Es Zone Relative Humidity %":39.2999992371,"AqlRfdQi Power (Calc)":0.0287630593,"9tAKv3tG Setpoint Temperature":58,"L4Vb3H0J Schedule":null,"Kamr4cZz Supply Air Temperature":63.0250015259,"QNupgV5D Supply Relative Humidity Setpoint %":30,"OratacDL Supply Relative Humidity %":50.2249984741,"b1eBcHjc Return Air Temperature":73.8249969482,"type":"AHU","subType":"","Status":true},"2020-04-18T20:45:00.000Z":{"dymclFPd Zone Temperature":71.7249984741,"ygZXCNrx Humidifier Valve %":0,"dECNkkkx Duct Static Pressure":0.5,"JJTf4KIN Mixed Air Temperature":68.4250030518,"ejzJNJVA TvG2WGjE Flow Setpoint":750,"QaxazYRs Pre Heating Temp":66.2249984741,"ymhl1rIT Static Pressure Setpoint":0.5,"7J5Znp6z Preheat Valve %":0,"m99GC7uz Supply Fan Output %":12.1800575256,"3p3Wd2Zp Cooling Valve %":0,"nqWMaKsU hq1bHbcu Flow":1.2750910521,"iAtum58lYXB6Es Zone Relative Humidity %":39.5499992371,"AqlRfdQi Power (Calc)":0.028989044,"9tAKv3tG Setpoint Temperature":58,"L4Vb3H0J Schedule":null,"Kamr4cZz Supply Air Temperature":63.2750015259,"QNupgV5D Supply Relative Humidity Setpoint %":30,"OratacDL Supply Relative Humidity %":49.9000015259,"b1eBcHjc Return Air Temperature":73.9000015259,"type":"AHU","subType":"","Status":true},"2020-04-18T21:00:00.000Z":{"dymclFPd Zone Temperature":71.75,"ygZXCNrx Humidifier Valve %":0,"dECNkkkx Duct Static Pressure":0.5,"JJTf4KIN Mixed Air Temperature":68.75,"ejzJNJVA TvG2WGjE Flow Setpoint":750,"QaxazYRs Pre Heating Temp":66.625,"ymhl1rIT Static Pressure Setpoint":0.5,"7J5Znp6z Preheat Valve %":0,"m99GC7uz Supply Fan Output %":12.1865682602,"3p3Wd2Zp Cooling Valve %":0,"nqWMaKsU hq1bHbcu Flow":1.3935585022,"iAtum58lYXB6Es Zone Relative Humidity %":39.3250007629,"AqlRfdQi Power (Calc)":0.0290355563,"9tAKv3tG Setpoint Temperature":58,"L4Vb3H0J Schedule":null,"Kamr4cZz Supply Air Temperature":63.3250007629,"QNupgV5D Supply Relative Humidity Setpoint %":30,"OratacDL Supply Relative Humidity %":49.9000015259,"b1eBcHjc Return Air Temperature":73.9749984741,"type":"AHU","subType":"","Status":true},"2020-04-18T21:15:00.000Z":{"dymclFPd Zone Temperature":71.75,"ygZXCNrx Humidifier Valve %":0,"dECNkkkx Duct Static Pressure":0.5,"JJTf4KIN Mixed Air Temperature":68.5999984741,"ejzJNJVA TvG2WGjE Flow Setpoint":750,"QaxazYRs Pre Heating Temp":66.8249969482,"ymhl1rIT Static Pressure Setpoint":0.5,"7J5Znp6z Preheat Valve %":0,"m99GC7uz Supply Fan Output %":12.1871566772,"3p3Wd2Zp Cooling Valve %":0,"nqWMaKsU hq1bHbcu Flow":1.3318659067,"iAtum58lYXB6Es Zone Relative Humidity %":39.2999992371,"AqlRfdQi Power (Calc)":0.0290397623,"9tAKv3tG Setpoint Temperature":58,"L4Vb3H0J Schedule":null,"Kamr4cZz Supply Air Temperature":63.3250007629,"QNupgV5D Supply Relative Humidity Setpoint %":30,"OratacDL Supply Relative Humidity %":49.9500007629,"b1eBcHjc Return Air Temperature":73.9749984741,"type":"AHU","subType":"","Status":true},"2020-04-18T21:30:00.000Z":{"dymclFPd Zone Temperature":71.7750015259,"ygZXCNrx Humidifier Valve %":0,"dECNkkkx Duct Static Pressure":0.5,"JJTf4KIN Mixed Air Temperature":68.3499984741,"ejzJNJVA TvG2WGjE Flow Setpoint":750,"QaxazYRs Pre Heating Temp":66.0749969482,"ymhl1rIT Static Pressure Setpoint":0.5,"7J5Znp6z Preheat Valve %":0,"m99GC7uz Supply Fan Output %":12.183889389,"3p3Wd2Zp Cooling Valve %":0,"nqWMaKsU hq1bHbcu Flow":1.4054354429,"iAtum58lYXB6Es Zone Relative Humidity %":39.4249992371,"AqlRfdQi Power (Calc)":0.0290164126,"9tAKv3tG Setpoint Temperature":58,"L4Vb3H0J Schedule":null,"Kamr4cZz Supply Air Temperature":63.3499984741,"QNupgV5D Supply Relative Humidity Setpoint %":30,"OratacDL Supply Relative Humidity %":50.0499992371,"b1eBcHjc Return Air Temperature":74.0250015259,"type":"AHU","subType":"","Status":true},"2020-04-18T21:45:00.000Z":{"dymclFPd Zone Temperature":71.8249969482,"ygZXCNrx Humidifier Valve %":0,"dECNkkkx Duct Static Pressure":0.5,"JJTf4KIN Mixed Air Temperature":68.6500015259,"ejzJNJVA TvG2WGjE Flow Setpoint":750,"QaxazYRs Pre Heating Temp":66.1750030518,"ymhl1rIT Static Pressure Setpoint":0.5,"7J5Znp6z Preheat Valve %":0,"m99GC7uz Supply Fan Output %":12.1840801239,"3p3Wd2Zp Cooling Valve %":0,"nqWMaKsU hq1bHbcu Flow":1.250426054,"iAtum58lYXB6Es Zone Relative Humidity %":39.2249984741,"AqlRfdQi Power (Calc)":0.0290177753,"9tAKv3tG Setpoint Temperature":58,"L4Vb3H0J Schedule":null,"Kamr4cZz Supply Air Temperature":63.375,"QNupgV5D Supply Relative Humidity Setpoint %":30,"OratacDL Supply Relative Humidity %":50.0750007629,"b1eBcHjc Return Air Temperature":74.0749969482,"type":"AHU","subType":"","Status":true},"2020-04-18T22:00:00.000Z":{"dymclFPd Zone Temperature":71.8499984741,"ygZXCNrx Humidifier Valve %":0,"dECNkkkx Duct Static Pressure":0.5,"JJTf4KIN Mixed Air Temperature":68.5999984741,"ejzJNJVA TvG2WGjE Flow Setpoint":750,"QaxazYRs Pre Heating Temp":66.3249969482,"ymhl1rIT Static Pressure Setpoint":0.5,"7J5Znp6z Preheat Valve %":0,"m99GC7uz Supply Fan Output %":12.182964325,"3p3Wd2Zp Cooling Valve %":0,"nqWMaKsU hq1bHbcu Flow":1.3420319557,"iAtum58lYXB6Es Zone Relative Humidity %":39.3250007629,"AqlRfdQi Power (Calc)":0.0290098038,"9tAKv3tG Setpoint Temperature":58,"L4Vb3H0J Schedule":null,"Kamr4cZz Supply Air Temperature":63.375,"QNupgV5D Supply Relative Humidity Setpoint %":30,"OratacDL Supply Relative Humidity %":50.125,"b1eBcHjc Return Air Temperature":74.0500030518,"type":"AHU","subType":"","Status":true},"2020-04-18T22:15:00.000Z":{"dymclFPd Zone Temperature":71.875,"ygZXCNrx Humidifier Valve %":0,"dECNkkkx Duct Static Pressure":0.5,"JJTf4KIN Mixed Air Temperature":68.3249969482,"ejzJNJVA TvG2WGjE Flow Setpoint":750,"QaxazYRs Pre Heating Temp":66.4499969482,"ymhl1rIT Static Pressure Setpoint":0.5,"7J5Znp6z Preheat Valve %":0,"m99GC7uz Supply Fan Output %":12.1789188385,"3p3Wd2Zp Cooling Valve %":0,"nqWMaKsU hq1bHbcu Flow":1.4003454447,"iAtum58lYXB6Es Zone Relative Humidity %":39.3499984741,"AqlRfdQi Power (Calc)":0.0289809144,"9tAKv3tG Setpoint Temperature":58,"L4Vb3H0J Schedule":null,"Kamr4cZz Supply Air Temperature":63.4000015259,"QNupgV5D Supply Relative Humidity Setpoint %":30,"OratacDL Supply Relative Humidity %":50.1749992371,"b1eBcHjc Return Air Temperature":74.1500015259,"type":"AHU","subType":"","Status":true},"2020-04-18T22:30:00.000Z":{"dymclFPd Zone Temperature":71.9499969482,"ygZXCNrx Humidifier Valve %":0,"dECNkkkx Duct Static Pressure":0.5,"JJTf4KIN Mixed Air Temperature":68.5749969482,"ejzJNJVA TvG2WGjE Flow Setpoint":750,"QaxazYRs Pre Heating Temp":66.2750015259,"ymhl1rIT Static Pressure Setpoint":0.5,"7J5Znp6z Preheat Valve %":0,"m99GC7uz Supply Fan Output %":12.1844072342,"3p3Wd2Zp Cooling Valve %":0,"nqWMaKsU hq1bHbcu Flow":1.3036214113,"iAtum58lYXB6Es Zone Relative Humidity %":39.375,"AqlRfdQi Power (Calc)":0.0290201125,"9tAKv3tG Setpoint Temperature":58,"L4Vb3H0J Schedule":null,"Kamr4cZz Supply Air Temperature":63.4249992371,"QNupgV5D Supply Relative Humidity Setpoint %":30,"OratacDL Supply Relative Humidity %":50.2249984741,"b1eBcHjc Return Air Temperature":74.1999969482,"type":"AHU","subType":"","Status":true},"2020-04-18T22:45:00.000Z":{"dymclFPd Zone Temperature":71.9749984741,"ygZXCNrx Humidifier Valve %":0,"dECNkkkx Duct Static Pressure":0.5,"JJTf4KIN Mixed Air Temperature":68.3499984741,"ejzJNJVA TvG2WGjE Flow Setpoint":750,"QaxazYRs Pre Heating Temp":65.7249984741,"ymhl1rIT Static Pressure Setpoint":0.5,"7J5Znp6z Preheat Valve %":0,"m99GC7uz Supply Fan Output %":12.195400238,"3p3Wd2Zp Cooling Valve %":0,"nqWMaKsU hq1bHbcu Flow":1.4081864357,"iAtum58lYXB6Es Zone Relative Humidity %":39.5250015259,"AqlRfdQi Power (Calc)":0.0290987309,"9tAKv3tG Setpoint Temperature":58,"L4Vb3H0J Schedule":null,"Kamr4cZz Supply Air Temperature":63.4249992371,"QNupgV5D Supply Relative Humidity Setpoint %":30,"OratacDL Supply Relative Humidity %":50.2750015259,"b1eBcHjc Return Air Temperature":74.1999969482,"type":"AHU","subType":"","Status":true},"2020-04-18T23:00:00.000Z":{"dymclFPd Zone Temperature":72.0250015259,"ygZXCNrx Humidifier Valve %":0,"dECNkkkx Duct Static Pressure":0.5,"JJTf4KIN Mixed Air Temperature":68.1750030518,"ejzJNJVA TvG2WGjE Flow Setpoint":750,"QaxazYRs Pre Heating Temp":66.0250015259,"ymhl1rIT Static Pressure Setpoint":0.5,"7J5Znp6z Preheat Valve %":0,"m99GC7uz Supply Fan Output %":12.1520013809,"3p3Wd2Zp Cooling Valve %":0,"nqWMaKsU hq1bHbcu Flow":1.4280661345,"iAtum58lYXB6Es Zone Relative Humidity %":39.5250015259,"AqlRfdQi Power (Calc)":0.0287891807,"9tAKv3tG Setpoint Temperature":58,"L4Vb3H0J Schedule":null,"Kamr4cZz Supply Air Temperature":61.5,"QNupgV5D Supply Relative Humidity Setpoint %":30,"OratacDL Supply Relative Humidity %":53.8250007629,"b1eBcHjc Return Air Temperature":74.2249984741,"type":"AHU","subType":"","Status":true},"2020-04-18T23:15:00.000Z":{"dymclFPd Zone Temperature":72.0500030518,"ygZXCNrx Humidifier Valve %":0,"dECNkkkx Duct Static Pressure":0.5,"JJTf4KIN Mixed Air Temperature":68.4250030518,"ejzJNJVA TvG2WGjE Flow Setpoint":750,"QaxazYRs Pre Heating Temp":65.9749984741,"ymhl1rIT Static Pressure Setpoint":0.5,"7J5Znp6z Preheat Valve %":0,"m99GC7uz Supply Fan Output %":12.1216068268,"3p3Wd2Zp Cooling Valve %":0,"nqWMaKsU hq1bHbcu Flow":1.2932357788,"iAtum58lYXB6Es Zone Relative Humidity %":39.5750007629,"AqlRfdQi Power (Calc)":0.0285736983,"9tAKv3tG Setpoint Temperature":58,"L4Vb3H0J Schedule":null,"Kamr4cZz Supply Air Temperature":61.2999992371,"QNupgV5D Supply Relative Humidity Setpoint %":30,"OratacDL Supply Relative Humidity %":54.2000007629,"b1eBcHjc Return Air Temperature":74.1999969482,"type":"AHU","subType":"","Status":true},"2020-04-18T23:30:00.000Z":{"dymclFPd Zone Temperature":72.0749969482,"ygZXCNrx Humidifier Valve %":0,"dECNkkkx Duct Static Pressure":0.5,"JJTf4KIN Mixed Air Temperature":68.4749984741,"ejzJNJVA TvG2WGjE Flow Setpoint":750,"QaxazYRs Pre Heating Temp":66.1750030518,"ymhl1rIT Static Pressure Setpoint":0.5,"7J5Znp6z Preheat Valve %":0,"m99GC7uz Supply Fan Output %":12.1195573807,"3p3Wd2Zp Cooling Valve %":0,"nqWMaKsU hq1bHbcu Flow":1.286346674,"iAtum58lYXB6Es Zone Relative Humidity %":39.4249992371,"AqlRfdQi Power (Calc)":0.0285592075,"9tAKv3tG Setpoint Temperature":58,"L4Vb3H0J Schedule":null,"Kamr4cZz Supply Air Temperature":61.2999992371,"QNupgV5D Supply Relative Humidity Setpoint %":30,"OratacDL Supply Relative Humidity %":54.2750015259,"b1eBcHjc Return Air Temperature":74.1999969482,"type":"AHU","subType":"","Status":true},"2020-04-18T23:45:00.000Z":{"dymclFPd Zone Temperature":72.0500030518,"ygZXCNrx Humidifier Valve %":0,"dECNkkkx Duct Static Pressure":0.5,"JJTf4KIN Mixed Air Temperature":68.25,"ejzJNJVA TvG2WGjE Flow Setpoint":750,"QaxazYRs Pre Heating Temp":66.4000015259,"ymhl1rIT Static Pressure Setpoint":0.5,"7J5Znp6z Preheat Valve %":0,"m99GC7uz Supply Fan Output %":12.1052036285,"3p3Wd2Zp Cooling Valve %":0,"nqWMaKsU hq1bHbcu Flow":1.4071911573,"iAtum58lYXB6Es Zone Relative Humidity %":39.7000007629,"AqlRfdQi Power (Calc)":0.0284578557,"9tAKv3tG Setpoint Temperature":58,"L4Vb3H0J Schedule":null,"Kamr4cZz Supply Air Temperature":61.2750015259,"QNupgV5D Supply Relative Humidity Setpoint %":30,"OratacDL Supply Relative Humidity %":54.2750015259,"b1eBcHjc Return Air Temperature":74.1999969482,"type":"AHU","subType":"","Status":true},"2020-04-19T00:00:00.000Z":{"dymclFPd Zone Temperature":72.0500030518,"ygZXCNrx Humidifier Valve %":0,"dECNkkkx Duct Static Pressure":0.5,"JJTf4KIN Mixed Air Temperature":68.6500015259,"ejzJNJVA TvG2WGjE Flow Setpoint":750,"QaxazYRs Pre Heating Temp":66.1500015259,"ymhl1rIT Static Pressure Setpoint":0.5,"7J5Znp6z Preheat Valve %":0,"m99GC7uz Supply Fan Output %":12.101773262,"3p3Wd2Zp Cooling Valve %":0,"nqWMaKsU hq1bHbcu Flow":1.2555660009,"iAtum58lYXB6Es Zone Relative Humidity %":39.5,"AqlRfdQi Power (Calc)":0.0284336694,"9tAKv3tG Setpoint Temperature":58,"L4Vb3H0J Schedule":null,"Kamr4cZz Supply Air Temperature":61.2750015259,"QNupgV5D Supply Relative Humidity Setpoint %":30,"OratacDL Supply Relative Humidity %":54.3250007629,"b1eBcHjc Return Air Temperature":74.1999969482,"type":"AHU","subType":"","Status":true},"2020-04-19T00:15:00.000Z":{"dymclFPd Zone Temperature":72.0500030518,"ygZXCNrx Humidifier Valve %":0,"dECNkkkx Duct Static Pressure":0.5,"JJTf4KIN Mixed Air Temperature":68.8249969482,"ejzJNJVA TvG2WGjE Flow Setpoint":750,"QaxazYRs Pre Heating Temp":65.8499984741,"ymhl1rIT Static Pressure Setpoint":0.5,"7J5Znp6z Preheat Valve %":0,"m99GC7uz Supply Fan Output %":12.0433740616,"3p3Wd2Zp Cooling Valve %":0,"nqWMaKsU hq1bHbcu Flow":1.3724423647,"iAtum58lYXB6Es Zone Relative Humidity %":39.3499984741,"AqlRfdQi Power (Calc)":0.0280240179,"9tAKv3tG Setpoint Temperature":58,"L4Vb3H0J Schedule":null,"Kamr4cZz Supply Air Temperature":61.2249984741,"QNupgV5D Supply Relative Humidity Setpoint %":30,"OratacDL Supply Relative Humidity %":54.3499984741,"b1eBcHjc Return Air Temperature":74.2249984741,"type":"AHU","subType":"","Status":true},"2020-04-19T00:30:00.000Z":{"dymclFPd Zone Temperature":72.0500030518,"ygZXCNrx Humidifier Valve %":0,"dECNkkkx Duct Static Pressure":0.5,"JJTf4KIN Mixed Air Temperature":68.5749969482,"ejzJNJVA TvG2WGjE Flow Setpoint":750,"QaxazYRs Pre Heating Temp":66.25,"ymhl1rIT Static Pressure Setpoint":0.5,"7J5Znp6z Preheat Valve %":0,"m99GC7uz Supply Fan Output %":12.0298061371,"3p3Wd2Zp Cooling Valve %":0,"nqWMaKsU hq1bHbcu Flow":1.2603468895,"iAtum58lYXB6Es Zone Relative Humidity %":39.4749984741,"AqlRfdQi Power (Calc)":0.0279294099,"9tAKv3tG Setpoint Temperature":58,"L4Vb3H0J Schedule":null,"Kamr4cZz Supply Air Temperature":61.25,"QNupgV5D Supply Relative Humidity Setpoint %":30,"OratacDL Supply Relative Humidity %":54.3499984741,"b1eBcHjc Return Air Temperature":74.25,"type":"AHU","subType":"","Status":true},"2020-04-19T00:45:00.000Z":{"dymclFPd Zone Temperature":72.0500030518,"ygZXCNrx Humidifier Valve %":0,"dECNkkkx Duct Static Pressure":0.5,"JJTf4KIN Mixed Air Temperature":68.0999984741,"ejzJNJVA TvG2WGjE Flow Setpoint":750,"QaxazYRs Pre Heating Temp":65.8000030518,"ymhl1rIT Static Pressure Setpoint":0.5,"7J5Znp6z Preheat Valve %":0,"m99GC7uz Supply Fan Output %":12.0155239105,"3p3Wd2Zp Cooling Valve %":0,"nqWMaKsU hq1bHbcu Flow":1.3079835176,"iAtum58lYXB6Es Zone Relative Humidity %":39.5750007629,"AqlRfdQi Power (Calc)":0.0278300515,"9tAKv3tG Setpoint Temperature":58,"L4Vb3H0J Schedule":null,"Kamr4cZz Supply Air Temperature":61.25,"QNupgV5D Supply Relative Humidity Setpoint %":30,"OratacDL Supply Relative Humidity %":54.375,"b1eBcHjc Return Air Temperature":74.2249984741,"type":"AHU","subType":"","Status":true},"2020-04-19T01:00:00.000Z":{"dymclFPd Zone Temperature":72.0,"ygZXCNrx Humidifier Valve %":0,"dECNkkkx Duct Static Pressure":0.5,"JJTf4KIN Mixed Air Temperature":68.1999969482,"ejzJNJVA TvG2WGjE Flow Setpoint":750,"QaxazYRs Pre Heating Temp":65.375,"ymhl1rIT Static Pressure Setpoint":0.5,"7J5Znp6z Preheat Valve %":0,"m99GC7uz Supply Fan Output %":12.0224990845,"3p3Wd2Zp Cooling Valve %":0,"nqWMaKsU hq1bHbcu Flow":1.4277020693,"iAtum58lYXB6Es Zone Relative Humidity %":39.625,"AqlRfdQi Power (Calc)":0.0278785468,"9tAKv3tG Setpoint Temperature":58,"L4Vb3H0J Schedule":null,"Kamr4cZz Supply Air Temperature":61.2249984741,"QNupgV5D Supply Relative Humidity Setpoint %":30,"OratacDL Supply Relative Humidity %":54.3250007629,"b1eBcHjc Return Air Temperature":74.25,"type":"AHU","subType":"","Status":true},"2020-04-19T01:15:00.000Z":{"dymclFPd Zone Temperature":71.9749984741,"ygZXCNrx Humidifier Valve %":0,"dECNkkkx Duct Static Pressure":0.5,"JJTf4KIN Mixed Air Temperature":68.1750030518,"ejzJNJVA TvG2WGjE Flow Setpoint":750,"QaxazYRs Pre Heating Temp":65.9749984741,"ymhl1rIT Static Pressure Setpoint":0.5,"7J5Znp6z Preheat Valve %":0,"m99GC7uz Supply Fan Output %":12.0194625854,"3p3Wd2Zp Cooling Valve %":0,"nqWMaKsU hq1bHbcu Flow":1.3180627823,"iAtum58lYXB6Es Zone Relative Humidity %":39.5750007629,"AqlRfdQi Power (Calc)":0.0278574285,"9tAKv3tG Setpoint Temperature":58,"L4Vb3H0J Schedule":null,"Kamr4cZz Supply Air Temperature":61.2750015259,"QNupgV5D Supply Relative Humidity Setpoint %":30,"OratacDL Supply Relative Humidity %":54.2999992371,"b1eBcHjc Return Air Temperature":74.2750015259,"type":"AHU","subType":"","Status":true},"2020-04-19T01:30:00.000Z":{"dymclFPd Zone Temperature":71.9499969482,"ygZXCNrx Humidifier Valve %":0,"dECNkkkx Duct Static Pressure":0.5,"JJTf4KIN Mixed Air Temperature":67.8499984741,"ejzJNJVA TvG2WGjE Flow Setpoint":750,"QaxazYRs Pre Heating Temp":65.0749969482,"ymhl1rIT Static Pressure Setpoint":0.5,"7J5Znp6z Preheat Valve %":0,"m99GC7uz Supply Fan Output %":12.0171966553,"3p3Wd2Zp Cooling Valve %":0,"nqWMaKsU hq1bHbcu Flow":1.3328256607,"iAtum58lYXB6Es Zone Relative Humidity %":39.7000007629,"AqlRfdQi Power (Calc)":0.0278416763,"9tAKv3tG Setpoint Temperature":58,"L4Vb3H0J Schedule":null,"Kamr4cZz Supply Air Temperature":61.25,"QNupgV5D Supply Relative Humidity Setpoint %":30,"OratacDL Supply Relative Humidity %":54.375,"b1eBcHjc Return Air Temperature":74.1999969482,"type":"AHU","subType":"","Status":true},"2020-04-19T01:45:00.000Z":{"dymclFPd Zone Temperature":71.9250030518,"ygZXCNrx Humidifier Valve %":0,"dECNkkkx Duct Static Pressure":0.5,"JJTf4KIN Mixed Air Temperature":67.7750015259,"ejzJNJVA TvG2WGjE Flow Setpoint":750,"QaxazYRs Pre Heating Temp":66.0250015259,"ymhl1rIT Static Pressure Setpoint":0.5,"7J5Znp6z Preheat Valve %":0,"m99GC7uz Supply Fan Output %":12.0196533203,"3p3Wd2Zp Cooling Valve %":0,"nqWMaKsU hq1bHbcu Flow":1.289247632,"iAtum58lYXB6Es Zone Relative Humidity %":39.5250015259,"AqlRfdQi Power (Calc)":0.0278587547,"9tAKv3tG Setpoint Temperature":58,"L4Vb3H0J Schedule":null,"Kamr4cZz Supply Air Temperature":61.2750015259,"QNupgV5D Supply Relative Humidity Setpoint %":30,"OratacDL Supply Relative Humidity %":54.2999992371,"b1eBcHjc Return Air Temperature":74.2750015259,"type":"AHU","subType":"","Status":true},"2020-04-19T02:00:00.000Z":{"dymclFPd Zone Temperature":71.9250030518,"ygZXCNrx Humidifier Valve %":0,"dECNkkkx Duct Static Pressure":0.5,"JJTf4KIN Mixed Air Temperature":66.9000015259,"ejzJNJVA TvG2WGjE Flow Setpoint":750,"QaxazYRs Pre Heating Temp":65.5,"ymhl1rIT Static Pressure Setpoint":0.5,"7J5Znp6z Preheat Valve %":0,"m99GC7uz Supply Fan Output %":12.015048027,"3p3Wd2Zp Cooling Valve %":0,"nqWMaKsU hq1bHbcu Flow":1.3774938583,"iAtum58lYXB6Es Zone Relative Humidity %":39.5499992371,"AqlRfdQi Power (Calc)":0.027826745,"9tAKv3tG Setpoint Temperature":58,"L4Vb3H0J Schedule":null,"Kamr4cZz Supply Air Temperature":61.25,"QNupgV5D Supply Relative Humidity Setpoint %":30,"OratacDL Supply Relative Humidity %":54.2999992371,"b1eBcHjc Return Air Temperature":74.1999969482,"type":"AHU","subType":"","Status":true},"2020-04-19T02:15:00.000Z":{"dymclFPd Zone Temperature":71.9000015259,"ygZXCNrx Humidifier Valve %":0,"dECNkkkx Duct Static Pressure":0.5,"JJTf4KIN Mixed Air Temperature":67.5749969482,"ejzJNJVA TvG2WGjE Flow Setpoint":750,"QaxazYRs Pre Heating Temp":65.3249969482,"ymhl1rIT Static Pressure Setpoint":0.5,"7J5Znp6z Preheat Valve %":0,"m99GC7uz Supply Fan Output %":12.0094051361,"3p3Wd2Zp Cooling Valve %":0,"nqWMaKsU hq1bHbcu Flow":1.2642065287,"iAtum58lYXB6Es Zone Relative Humidity %":39.6500015259,"AqlRfdQi Power (Calc)":0.0277875567,"9tAKv3tG Setpoint Temperature":58,"L4Vb3H0J Schedule":null,"Kamr4cZz Supply Air Temperature":62.0250015259,"QNupgV5D Supply Relative Humidity Setpoint %":30,"OratacDL Supply Relative Humidity %":52.75,"b1eBcHjc Return Air Temperature":74.2249984741,"type":"AHU","subType":"","Status":true},"2020-04-19T02:30:00.000Z":{"dymclFPd Zone Temperature":71.9000015259,"ygZXCNrx Humidifier Valve %":0,"dECNkkkx Duct Static Pressure":0.5,"JJTf4KIN Mixed Air Temperature":67.6750030518,"ejzJNJVA TvG2WGjE Flow Setpoint":750,"QaxazYRs Pre Heating Temp":65.1999969482,"ymhl1rIT Static Pressure Setpoint":0.5,"7J5Znp6z Preheat Valve %":0,"m99GC7uz Supply Fan Output %":12.0289211273,"3p3Wd2Zp Cooling Valve %":0,"nqWMaKsU hq1bHbcu Flow":1.352325201,"iAtum58lYXB6Es Zone Relative Humidity %":39.7999992371,"AqlRfdQi Power (Calc)":0.0279232463,"9tAKv3tG Setpoint Temperature":58,"L4Vb3H0J Schedule":null,"Kamr4cZz Supply Air Temperature":62.5750007629,"QNupgV5D Supply Relative Humidity Setpoint %":30,"OratacDL Supply Relative Humidity %":51.8250007629,"b1eBcHjc Return Air Temperature":74.1999969482,"type":"AHU","subType":"","Status":true},"2020-04-19T02:45:00.000Z":{"dymclFPd Zone Temperature":71.875,"ygZXCNrx Humidifier Valve %":0,"dECNkkkx Duct Static Pressure":0.5,"JJTf4KIN Mixed Air Temperature":67.625,"ejzJNJVA TvG2WGjE Flow Setpoint":750,"QaxazYRs Pre Heating Temp":64.7750015259,"ymhl1rIT Static Pressure Setpoint":0.5,"7J5Znp6z Preheat Valve %":0,"m99GC7uz Supply Fan Output %":12.0647611618,"3p3Wd2Zp Cooling Valve %":0,"nqWMaKsU hq1bHbcu Flow":1.3228852749,"iAtum58lYXB6Es Zone Relative Humidity %":39.6500015259,"AqlRfdQi Power (Calc)":0.0281735816,"9tAKv3tG Setpoint Temperature":58,"L4Vb3H0J Schedule":null,"Kamr4cZz Supply Air Temperature":62.625,"QNupgV5D Supply Relative Humidity Setpoint %":30,"OratacDL Supply Relative Humidity %":51.7999992371,"b1eBcHjc Return Air Temperature":74.1999969482,"type":"AHU","subType":"","Status":true},"2020-04-19T03:00:00.000Z":{"dymclFPd Zone Temperature":71.875,"ygZXCNrx Humidifier Valve %":0,"dECNkkkx Duct Static Pressure":0.5,"JJTf4KIN Mixed Air Temperature":67.4499969482,"ejzJNJVA TvG2WGjE Flow Setpoint":750,"QaxazYRs Pre Heating Temp":64.3249969482,"ymhl1rIT Static Pressure Setpoint":0.5,"7J5Znp6z Preheat Valve %":0,"m99GC7uz Supply Fan Output %":12.1115922928,"3p3Wd2Zp Cooling Valve %":0,"nqWMaKsU hq1bHbcu Flow":1.4026446342,"iAtum58lYXB6Es Zone Relative Humidity %":39.9749984741,"AqlRfdQi Power (Calc)":0.0285029364,"9tAKv3tG Setpoint Temperature":58,"L4Vb3H0J Schedule":null,"Kamr4cZz Supply Air Temperature":62.5999984741,"QNupgV5D Supply Relative Humidity Setpoint %":30,"OratacDL Supply Relative Humidity %":51.75,"b1eBcHjc Return Air Temperature":74.1999969482,"type":"AHU","subType":"","Status":true},"2020-04-19T03:15:00.000Z":{"dymclFPd Zone Temperature":71.875,"ygZXCNrx Humidifier Valve %":0,"dECNkkkx Duct Static Pressure":0.5,"JJTf4KIN Mixed Air Temperature":67.8499984741,"ejzJNJVA TvG2WGjE Flow Setpoint":750,"QaxazYRs Pre Heating Temp":64.5749969482,"ymhl1rIT Static Pressure Setpoint":0.5,"7J5Znp6z Preheat Valve %":0,"m99GC7uz Supply Fan Output %":12.107129097,"3p3Wd2Zp Cooling Valve %":0,"nqWMaKsU hq1bHbcu Flow":1.2217600346,"iAtum58lYXB6Es Zone Relative Humidity %":39.5999984741,"AqlRfdQi Power (Calc)":0.0284714375,"9tAKv3tG Setpoint Temperature":58,"L4Vb3H0J Schedule":null,"Kamr4cZz Supply Air Temperature":62.5999984741,"QNupgV5D Supply Relative Humidity Setpoint %":30,"OratacDL Supply Relative Humidity %":51.7249984741,"b1eBcHjc Return Air Temperature":74.1500015259,"type":"AHU","subType":"","Status":true},"2020-04-19T03:30:00.000Z":{"dymclFPd Zone Temperature":71.875,"ygZXCNrx Humidifier Valve %":0,"dECNkkkx Duct Static Pressure":0.5,"JJTf4KIN Mixed Air Temperature":66.4499969482,"ejzJNJVA TvG2WGjE Flow Setpoint":750,"QaxazYRs Pre Heating Temp":63.8250007629,"ymhl1rIT Static Pressure Setpoint":0.5,"7J5Znp6z Preheat Valve %":0,"m99GC7uz Supply Fan Output %":12.1218757629,"3p3Wd2Zp Cooling Valve %":0,"nqWMaKsU hq1bHbcu Flow":1.2896794081,"iAtum58lYXB6Es Zone Relative Humidity %":39.8250007629,"AqlRfdQi Power (Calc)":0.0285756002,"9tAKv3tG Setpoint Temperature":58,"L4Vb3H0J Schedule":null,"Kamr4cZz Supply Air Temperature":62.5499992371,"QNupgV5D Supply Relative Humidity Setpoint %":30,"OratacDL Supply Relative Humidity %":51.75,"b1eBcHjc Return Air Temperature":74.1750030518,"type":"AHU","subType":"","Status":true},"2020-04-19T03:45:00.000Z":{"dymclFPd Zone Temperature":71.9000015259,"ygZXCNrx Humidifier Valve %":0,"dECNkkkx Duct Static Pressure":0.5,"JJTf4KIN Mixed Air Temperature":66.875,"ejzJNJVA TvG2WGjE Flow Setpoint":750,"QaxazYRs Pre Heating Temp":65.0749969482,"ymhl1rIT Static Pressure Setpoint":0.5,"7J5Znp6z Preheat Valve %":0,"m99GC7uz Supply Fan Output %":12.1264476776,"3p3Wd2Zp Cooling Valve %":0,"nqWMaKsU hq1bHbcu Flow":1.3881804943,"iAtum58lYXB6Es Zone Relative Humidity %":39.75,"AqlRfdQi Power (Calc)":0.0286079453,"9tAKv3tG Setpoint Temperature":58,"L4Vb3H0J Schedule":null,"Kamr4cZz Supply Air Temperature":62.5250015259,"QNupgV5D Supply Relative Humidity Setpoint %":30,"OratacDL Supply Relative Humidity %":51.75,"b1eBcHjc Return Air Temperature":74.1500015259,"type":"AHU","subType":"","Status":true},"2020-04-19T04:00:00.000Z":{"dymclFPd Zone Temperature":71.9000015259,"ygZXCNrx Humidifier Valve %":0,"dECNkkkx Duct Static Pressure":0.5,"JJTf4KIN Mixed Air Temperature":67.9499969482,"ejzJNJVA TvG2WGjE Flow Setpoint":750,"QaxazYRs Pre Heating Temp":65.3000030518,"ymhl1rIT Static Pressure Setpoint":0.5,"7J5Znp6z Preheat Valve %":0,"m99GC7uz Supply Fan Output %":12.1288871765,"3p3Wd2Zp Cooling Valve %":0,"nqWMaKsU hq1bHbcu Flow":1.3826617002,"iAtum58lYXB6Es Zone Relative Humidity %":39.9000015259,"AqlRfdQi Power (Calc)":0.0286252141,"9tAKv3tG Setpoint Temperature":58,"L4Vb3H0J Schedule":0.0,"Kamr4cZz Supply Air Temperature":62.5750007629,"QNupgV5D Supply Relative Humidity Setpoint %":30,"OratacDL Supply Relative Humidity %":51.5499992371,"b1eBcHjc Return Air Temperature":74.1500015259,"type":"AHU","subType":"","Status":true},"2020-04-19T04:15:00.000Z":{"dymclFPd Zone Temperature":71.875,"ygZXCNrx Humidifier Valve %":0,"dECNkkkx Duct Static Pressure":0.5,"JJTf4KIN Mixed Air Temperature":67.0749969482,"ejzJNJVA TvG2WGjE Flow Setpoint":750,"QaxazYRs Pre Heating Temp":64.8499984741,"ymhl1rIT Static Pressure Setpoint":0.5,"7J5Znp6z Preheat Valve %":0,"m99GC7uz Supply Fan Output %":12.1220197678,"3p3Wd2Zp Cooling Valve %":0,"nqWMaKsU hq1bHbcu Flow":1.3240380287,"iAtum58lYXB6Es Zone Relative Humidity %":39.8250007629,"AqlRfdQi Power (Calc)":0.0285766186,"9tAKv3tG Setpoint Temperature":58,"L4Vb3H0J Schedule":0.0,"Kamr4cZz Supply Air Temperature":62.5499992371,"QNupgV5D Supply Relative Humidity Setpoint %":30,"OratacDL Supply Relative Humidity %":51.5750007629,"b1eBcHjc Return Air Temperature":74.125,"type":"AHU","subType":"","Status":true},"2020-04-19T04:30:00.000Z":{"dymclFPd Zone Temperature":71.9000015259,"ygZXCNrx Humidifier Valve %":0,"dECNkkkx Duct Static Pressure":0.5,"JJTf4KIN Mixed Air Temperature":66.875,"ejzJNJVA TvG2WGjE Flow Setpoint":750,"QaxazYRs Pre Heating Temp":64.375,"ymhl1rIT Static Pressure Setpoint":0.5,"7J5Znp6z Preheat Valve %":0,"m99GC7uz Supply Fan Output %":12.1248464584,"3p3Wd2Zp Cooling Valve %":0,"nqWMaKsU hq1bHbcu Flow":1.5226272345,"iAtum58lYXB6Es Zone Relative Humidity %":39.7249984741,"AqlRfdQi Power (Calc)":0.0285966143,"9tAKv3tG Setpoint Temperature":58,"L4Vb3H0J Schedule":0.0,"Kamr4cZz Supply Air Temperature":62.5499992371,"QNupgV5D Supply Relative Humidity Setpoint %":30,"OratacDL Supply Relative Humidity %":51.5750007629,"b1eBcHjc Return Air Temperature":74.0999984741,"type":"AHU","subType":"","Status":true},"2020-04-19T04:45:00.000Z":{"dymclFPd Zone Temperature":71.875,"ygZXCNrx Humidifier Valve %":0,"dECNkkkx Duct Static Pressure":0.5,"JJTf4KIN Mixed Air Temperature":66.9499969482,"ejzJNJVA TvG2WGjE Flow Setpoint":750,"QaxazYRs Pre Heating Temp":65.0500030518,"ymhl1rIT Static Pressure Setpoint":0.5,"7J5Znp6z Preheat Valve %":0,"m99GC7uz Supply Fan Output %":12.1297311783,"3p3Wd2Zp Cooling Valve %":0,"nqWMaKsU hq1bHbcu Flow":1.2636909485,"iAtum58lYXB6Es Zone Relative Humidity %":39.9249992371,"AqlRfdQi Power (Calc)":0.0286311902,"9tAKv3tG Setpoint Temperature":58,"L4Vb3H0J Schedule":0.0,"Kamr4cZz Supply Air Temperature":62.5499992371,"QNupgV5D Supply Relative Humidity Setpoint %":30,"OratacDL Supply Relative Humidity %":51.5,"b1eBcHjc Return Air Temperature":74.0749969482,"type":"AHU","subType":"","Status":true},"2020-04-19T05:00:00.000Z":{"dymclFPd Zone Temperature":71.875,"ygZXCNrx Humidifier Valve %":0,"dECNkkkx Duct Static Pressure":0.5,"JJTf4KIN Mixed Air Temperature":67.375,"ejzJNJVA TvG2WGjE Flow Setpoint":750,"QaxazYRs Pre Heating Temp":64.9000015259,"ymhl1rIT Static Pressure Setpoint":0.5,"7J5Znp6z Preheat Valve %":0,"m99GC7uz Supply Fan Output %":12.1253824234,"3p3Wd2Zp Cooling Valve %":0,"nqWMaKsU hq1bHbcu Flow":1.4186327457,"iAtum58lYXB6Es Zone Relative Humidity %":39.7999992371,"AqlRfdQi Power (Calc)":0.0286004067,"9tAKv3tG Setpoint Temperature":58,"L4Vb3H0J Schedule":0.0,"Kamr4cZz Supply Air Temperature":62.5,"QNupgV5D Supply Relative Humidity Setpoint %":30,"OratacDL Supply Relative Humidity %":51.5499992371,"b1eBcHjc Return Air Temperature":74.0500030518,"type":"AHU","subType":"","Status":true},"2020-04-19T05:15:00.000Z":{"dymclFPd Zone Temperature":71.875,"ygZXCNrx Humidifier Valve %":0,"dECNkkkx Duct Static Pressure":0.5,"JJTf4KIN Mixed Air Temperature":68.1999969482,"ejzJNJVA TvG2WGjE Flow Setpoint":750,"QaxazYRs Pre Heating Temp":66.0,"ymhl1rIT Static Pressure Setpoint":0.5,"7J5Znp6z Preheat Valve %":0,"m99GC7uz Supply Fan Output %":12.1262664795,"3p3Wd2Zp Cooling Valve %":0,"nqWMaKsU hq1bHbcu Flow":1.4475702047,"iAtum58lYXB6Es Zone Relative Humidity %":39.9249992371,"AqlRfdQi Power (Calc)":0.0286066629,"9tAKv3tG Setpoint Temperature":58,"L4Vb3H0J Schedule":0.0,"Kamr4cZz Supply Air Temperature":62.5,"QNupgV5D Supply Relative Humidity Setpoint %":30,"OratacDL Supply Relative Humidity %":51.5,"b1eBcHjc Return Air Temperature":74.0749969482,"type":"AHU","subType":"","Status":true},"2020-04-19T05:30:00.000Z":{"dymclFPd Zone Temperature":71.875,"ygZXCNrx Humidifier Valve %":0,"dECNkkkx Duct Static Pressure":0.5,"JJTf4KIN Mixed Air Temperature":67.9000015259,"ejzJNJVA TvG2WGjE Flow Setpoint":750,"QaxazYRs Pre Heating Temp":65.7750015259,"ymhl1rIT Static Pressure Setpoint":0.5,"7J5Znp6z Preheat Valve %":0,"m99GC7uz Supply Fan Output %":12.1305742264,"3p3Wd2Zp Cooling Valve %":0,"nqWMaKsU hq1bHbcu Flow":1.3507913351,"iAtum58lYXB6Es Zone Relative Humidity %":39.7750015259,"AqlRfdQi Power (Calc)":0.0286371605,"9tAKv3tG Setpoint Temperature":58,"L4Vb3H0J Schedule":0.0,"Kamr4cZz Supply Air Temperature":62.5,"QNupgV5D Supply Relative Humidity Setpoint %":30,"OratacDL Supply Relative Humidity %":51.4749984741,"b1eBcHjc Return Air Temperature":74.0500030518,"type":"AHU","subType":"","Status":true},"2020-04-19T05:45:00.000Z":{"dymclFPd Zone Temperature":71.8249969482,"ygZXCNrx Humidifier Valve %":0,"dECNkkkx Duct Static Pressure":0.5,"JJTf4KIN Mixed Air Temperature":67.8000030518,"ejzJNJVA TvG2WGjE Flow Setpoint":750,"QaxazYRs Pre Heating Temp":65.5749969482,"ymhl1rIT Static Pressure Setpoint":0.5,"7J5Znp6z Preheat Valve %":0,"m99GC7uz Supply Fan Output %":12.1251802444,"3p3Wd2Zp Cooling Valve %":0,"nqWMaKsU hq1bHbcu Flow":1.4104373455,"iAtum58lYXB6Es Zone Relative Humidity %":40.0999984741,"AqlRfdQi Power (Calc)":0.0285989761,"9tAKv3tG Setpoint Temperature":58,"L4Vb3H0J Schedule":0.0,"Kamr4cZz Supply Air Temperature":62.5,"QNupgV5D Supply Relative Humidity Setpoint %":30,"OratacDL Supply Relative Humidity %":51.4500007629,"b1eBcHjc Return Air Temperature":74.0250015259,"type":"AHU","subType":"","Status":true},"2020-04-19T06:00:00.000Z":{"dymclFPd Zone Temperature":71.8499984741,"ygZXCNrx Humidifier Valve %":0,"dECNkkkx Duct Static Pressure":0.5,"JJTf4KIN Mixed Air Temperature":67.8000030518,"ejzJNJVA TvG2WGjE Flow Setpoint":750,"QaxazYRs Pre Heating Temp":65.625,"ymhl1rIT Static Pressure Setpoint":0.5,"7J5Znp6z Preheat Valve %":0,"m99GC7uz Supply Fan Output %":12.1214876175,"3p3Wd2Zp Cooling Valve %":0,"nqWMaKsU hq1bHbcu Flow":1.4304956198,"iAtum58lYXB6Es Zone Relative Humidity %":39.8250007629,"AqlRfdQi Power (Calc)":0.0285728553,"9tAKv3tG Setpoint Temperature":58,"L4Vb3H0J Schedule":0.0,"Kamr4cZz Supply Air Temperature":62.4749984741,"QNupgV5D Supply Relative Humidity Setpoint %":30,"OratacDL Supply Relative Humidity %":51.4500007629,"b1eBcHjc Return Air Temperature":73.9749984741,"type":"AHU","subType":"","Status":true},"2020-04-19T06:15:00.000Z":{"dymclFPd Zone Temperature":71.8499984741,"ygZXCNrx Humidifier Valve %":0,"dECNkkkx Duct Static Pressure":0.5,"JJTf4KIN Mixed Air Temperature":67.6999969482,"ejzJNJVA TvG2WGjE Flow Setpoint":750,"QaxazYRs Pre Heating Temp":65.8499984741,"ymhl1rIT Static Pressure Setpoint":0.5,"7J5Znp6z Preheat Valve %":0,"m99GC7uz Supply Fan Output %":12.1284570694,"3p3Wd2Zp Cooling Valve %":0,"nqWMaKsU hq1bHbcu Flow":1.342929244,"iAtum58lYXB6Es Zone Relative Humidity %":39.8250007629,"AqlRfdQi Power (Calc)":0.0286221689,"9tAKv3tG Setpoint Temperature":58,"L4Vb3H0J Schedule":0.0,"Kamr4cZz Supply Air Temperature":62.5250015259,"QNupgV5D Supply Relative Humidity Setpoint %":30,"OratacDL Supply Relative Humidity %":51.3250007629,"b1eBcHjc Return Air Temperature":73.9499969482,"type":"AHU","subType":"","Status":true},"2020-04-19T06:30:00.000Z":{"dymclFPd Zone Temperature":71.8249969482,"ygZXCNrx Humidifier Valve %":0,"dECNkkkx Duct Static Pressure":0.5,"JJTf4KIN Mixed Air Temperature":68.0500030518,"ejzJNJVA TvG2WGjE Flow Setpoint":750,"QaxazYRs Pre Heating Temp":66.0999984741,"ymhl1rIT Static Pressure Setpoint":0.5,"7J5Znp6z Preheat Valve %":0,"m99GC7uz Supply Fan Output %":12.1347732544,"3p3Wd2Zp Cooling Valve %":0,"nqWMaKsU hq1bHbcu Flow":1.395103693,"iAtum58lYXB6Es Zone Relative Humidity %":40.1500015259,"AqlRfdQi Power (Calc)":0.0286669093,"9tAKv3tG Setpoint Temperature":58,"L4Vb3H0J Schedule":0.0,"Kamr4cZz Supply Air Temperature":62.5499992371,"QNupgV5D Supply Relative Humidity Setpoint %":30,"OratacDL Supply Relative Humidity %":51.2000007629,"b1eBcHjc Return Air Temperature":73.9250030518,"type":"AHU","subType":"","Status":true},"2020-04-19T06:45:00.000Z":{"dymclFPd Zone Temperature":71.8000030518,"ygZXCNrx Humidifier Valve %":0,"dECNkkkx Duct Static Pressure":0.5,"JJTf4KIN Mixed Air Temperature":67.5500030518,"ejzJNJVA TvG2WGjE Flow Setpoint":750,"QaxazYRs Pre Heating Temp":65.4250030518,"ymhl1rIT Static Pressure Setpoint":0.5,"7J5Znp6z Preheat Valve %":0,"m99GC7uz Supply Fan Output %":12.1267280579,"3p3Wd2Zp Cooling Valve %":0,"nqWMaKsU hq1bHbcu Flow":1.2883634567,"iAtum58lYXB6Es Zone Relative Humidity %":40.0750007629,"AqlRfdQi Power (Calc)":0.0286099297,"9tAKv3tG Setpoint Temperature":58,"L4Vb3H0J Schedule":0.0,"Kamr4cZz Supply Air Temperature":62.5999984741,"QNupgV5D Supply Relative Humidity Setpoint %":30,"OratacDL Supply Relative Humidity %":51.0750007629,"b1eBcHjc Return Air Temperature":73.9250030518,"type":"AHU","subType":"","Status":true},"2020-04-19T07:00:00.000Z":{"dymclFPd Zone Temperature":71.8000030518,"ygZXCNrx Humidifier Valve %":0,"dECNkkkx Duct Static Pressure":0.5,"JJTf4KIN Mixed Air Temperature":66.7249984741,"ejzJNJVA TvG2WGjE Flow Setpoint":750,"QaxazYRs Pre Heating Temp":64.7750015259,"ymhl1rIT Static Pressure Setpoint":0.5,"7J5Znp6z Preheat Valve %":0,"m99GC7uz Supply Fan Output %":12.1134977341,"3p3Wd2Zp Cooling Valve %":0,"nqWMaKsU hq1bHbcu Flow":1.3710042238,"iAtum58lYXB6Es Zone Relative Humidity %":40.0499992371,"AqlRfdQi Power (Calc)":0.0285163911,"9tAKv3tG Setpoint Temperature":58,"L4Vb3H0J Schedule":0.0,"Kamr4cZz Supply Air Temperature":62.5,"QNupgV5D Supply Relative Humidity Setpoint %":30,"OratacDL Supply Relative Humidity %":51.1500015259,"b1eBcHjc Return Air Temperature":73.9250030518,"type":"AHU","subType":"","Status":true},"2020-04-19T07:15:00.000Z":{"dymclFPd Zone Temperature":71.7750015259,"ygZXCNrx Humidifier Valve %":0,"dECNkkkx Duct Static Pressure":0.5,"JJTf4KIN Mixed Air Temperature":67.4000015259,"ejzJNJVA TvG2WGjE Flow Setpoint":750,"QaxazYRs Pre Heating Temp":65.0500030518,"ymhl1rIT Static Pressure Setpoint":0.5,"7J5Znp6z Preheat Valve %":0,"m99GC7uz Supply Fan Output %":12.1113405228,"3p3Wd2Zp Cooling Valve %":0,"nqWMaKsU hq1bHbcu Flow":1.3702622652,"iAtum58lYXB6Es Zone Relative Humidity %":40.0499992371,"AqlRfdQi Power (Calc)":0.0285011589,"9tAKv3tG Setpoint Temperature":58,"L4Vb3H0J Schedule":0.0,"Kamr4cZz Supply Air Temperature":62.5,"QNupgV5D Supply Relative Humidity Setpoint %":30,"OratacDL Supply Relative Humidity %":51.0499992371,"b1eBcHjc Return Air Temperature":73.9749984741,"type":"AHU","subType":"","Status":true},"2020-04-19T07:30:00.000Z":{"dymclFPd Zone Temperature":71.7750015259,"ygZXCNrx Humidifier Valve %":0,"dECNkkkx Duct Static Pressure":0.5,"JJTf4KIN Mixed Air Temperature":67.2249984741,"ejzJNJVA TvG2WGjE Flow Setpoint":750,"QaxazYRs Pre Heating Temp":64.7750015259,"ymhl1rIT Static Pressure Setpoint":0.5,"7J5Znp6z Preheat Valve %":0,"m99GC7uz Supply Fan Output %":12.1080780029,"3p3Wd2Zp Cooling Valve %":0,"nqWMaKsU hq1bHbcu Flow":1.3995034695,"iAtum58lYXB6Es Zone Relative Humidity %":40.0,"AqlRfdQi Power (Calc)":0.0284781324,"9tAKv3tG Setpoint Temperature":58,"L4Vb3H0J Schedule":0.0,"Kamr4cZz Supply Air Temperature":62.4749984741,"QNupgV5D Supply Relative Humidity Setpoint %":30,"OratacDL Supply Relative Humidity %":51.0499992371,"b1eBcHjc Return Air Temperature":73.9000015259,"type":"AHU","subType":"","Status":true},"2020-04-19T07:45:00.000Z":{"dymclFPd Zone Temperature":71.75,"ygZXCNrx Humidifier Valve %":0,"dECNkkkx Duct Static Pressure":0.5,"JJTf4KIN Mixed Air Temperature":66.875,"ejzJNJVA TvG2WGjE Flow Setpoint":750,"QaxazYRs Pre Heating Temp":65.125,"ymhl1rIT Static Pressure Setpoint":0.5,"7J5Znp6z Preheat Valve %":0,"m99GC7uz Supply Fan Output %":12.1087360382,"3p3Wd2Zp Cooling Valve %":0,"nqWMaKsU hq1bHbcu Flow":1.410063982,"iAtum58lYXB6Es Zone Relative Humidity %":40.0750007629,"AqlRfdQi Power (Calc)":0.0284827757,"9tAKv3tG Setpoint Temperature":58,"L4Vb3H0J Schedule":0.0,"Kamr4cZz Supply Air Temperature":62.4749984741,"QNupgV5D Supply Relative Humidity Setpoint %":30,"OratacDL Supply Relative Humidity %":51.0,"b1eBcHjc Return Air Temperature":73.875,"type":"AHU","subType":"","Status":true},"2020-04-19T08:00:00.000Z":{"dymclFPd Zone Temperature":71.7750015259,"ygZXCNrx Humidifier Valve %":0,"dECNkkkx Duct Static Pressure":0.5,"JJTf4KIN Mixed Air Temperature":66.0,"ejzJNJVA TvG2WGjE Flow Setpoint":750,"QaxazYRs Pre Heating Temp":64.6500015259,"ymhl1rIT Static Pressure Setpoint":0.5,"7J5Znp6z Preheat Valve %":0,"m99GC7uz Supply Fan Output %":12.1046266556,"3p3Wd2Zp Cooling Valve %":0,"nqWMaKsU hq1bHbcu Flow":1.4264553785,"iAtum58lYXB6Es Zone Relative Humidity %":39.9000015259,"AqlRfdQi Power (Calc)":0.0284537867,"9tAKv3tG Setpoint Temperature":58,"L4Vb3H0J Schedule":0.0,"Kamr4cZz Supply Air Temperature":62.4500007629,"QNupgV5D Supply Relative Humidity Setpoint %":30,"OratacDL Supply Relative Humidity %":50.9749984741,"b1eBcHjc Return Air Temperature":73.8499984741,"type":"AHU","subType":"","Status":true},"2020-04-19T08:15:00.000Z":{"dymclFPd Zone Temperature":71.75,"ygZXCNrx Humidifier Valve %":0,"dECNkkkx Duct Static Pressure":0.5,"JJTf4KIN Mixed Air Temperature":67.6999969482,"ejzJNJVA TvG2WGjE Flow Setpoint":750,"QaxazYRs Pre Heating Temp":65.3000030518,"ymhl1rIT Static Pressure Setpoint":0.5,"7J5Znp6z Preheat Valve %":0,"m99GC7uz Supply Fan Output %":12.1085968018,"3p3Wd2Zp Cooling Valve %":0,"nqWMaKsU hq1bHbcu Flow":1.3843901157,"iAtum58lYXB6Es Zone Relative Humidity %":40.0750007629,"AqlRfdQi Power (Calc)":0.0284817932,"9tAKv3tG Setpoint Temperature":58,"L4Vb3H0J Schedule":0.0,"Kamr4cZz Supply Air Temperature":62.4500007629,"QNupgV5D Supply Relative Humidity Setpoint %":30,"OratacDL Supply Relative Humidity %":50.8250007629,"b1eBcHjc Return Air Temperature":73.8249969482,"type":"AHU","subType":"","Status":true},"2020-04-19T08:30:00.000Z":{"dymclFPd Zone Temperature":71.7249984741,"ygZXCNrx Humidifier Valve %":0,"dECNkkkx Duct Static Pressure":0.5,"JJTf4KIN Mixed Air Temperature":67.1500015259,"ejzJNJVA TvG2WGjE Flow Setpoint":750,"QaxazYRs Pre Heating Temp":64.8249969482,"ymhl1rIT Static Pressure Setpoint":0.5,"7J5Znp6z Preheat Valve %":0,"m99GC7uz Supply Fan Output %":12.1185913086,"3p3Wd2Zp Cooling Valve %":0,"nqWMaKsU hq1bHbcu Flow":1.3599740267,"iAtum58lYXB6Es Zone Relative Humidity %":40.0750007629,"AqlRfdQi Power (Calc)":0.0285523785,"9tAKv3tG Setpoint Temperature":58,"L4Vb3H0J Schedule":0.0,"Kamr4cZz Supply Air Temperature":62.4500007629,"QNupgV5D Supply Relative Humidity Setpoint %":30,"OratacDL Supply Relative Humidity %":50.7999992371,"b1eBcHjc Return Air Temperature":73.8000030518,"type":"AHU","subType":"","Status":true},"2020-04-19T08:45:00.000Z":{"dymclFPd Zone Temperature":71.6999969482,"ygZXCNrx Humidifier Valve %":0,"dECNkkkx Duct Static Pressure":0.5,"JJTf4KIN Mixed Air Temperature":67.3249969482,"ejzJNJVA TvG2WGjE Flow Setpoint":750,"QaxazYRs Pre Heating Temp":65.4749984741,"ymhl1rIT Static Pressure Setpoint":0.5,"7J5Znp6z Preheat Valve %":0,"m99GC7uz Supply Fan Output %":12.1116218567,"3p3Wd2Zp Cooling Valve %":0,"nqWMaKsU hq1bHbcu Flow":1.3562552929,"iAtum58lYXB6Es Zone Relative Humidity %":39.9500007629,"AqlRfdQi Power (Calc)":0.0285031451,"9tAKv3tG Setpoint Temperature":58,"L4Vb3H0J Schedule":0.0,"Kamr4cZz Supply Air Temperature":62.4249992371,"QNupgV5D Supply Relative Humidity Setpoint %":30,"OratacDL Supply Relative Humidity %":50.7999992371,"b1eBcHjc Return Air Temperature":73.7750015259,"type":"AHU","subType":"","Status":true},"2020-04-19T09:00:00.000Z":{"dymclFPd Zone Temperature":71.6999969482,"ygZXCNrx Humidifier Valve %":0,"dECNkkkx Duct Static Pressure":0.5,"JJTf4KIN Mixed Air Temperature":66.7750015259,"ejzJNJVA TvG2WGjE Flow Setpoint":750,"QaxazYRs Pre Heating Temp":64.25,"ymhl1rIT Static Pressure Setpoint":0.5,"7J5Znp6z Preheat Valve %":0,"m99GC7uz Supply Fan Output %":12.1112413406,"3p3Wd2Zp Cooling Valve %":0,"nqWMaKsU hq1bHbcu Flow":1.4397794008,"iAtum58lYXB6Es Zone Relative Humidity %":40.2249984741,"AqlRfdQi Power (Calc)":0.0285004587,"9tAKv3tG Setpoint Temperature":58,"L4Vb3H0J Schedule":0.0,"Kamr4cZz Supply Air Temperature":62.375,"QNupgV5D Supply Relative Humidity Setpoint %":30,"OratacDL Supply Relative Humidity %":50.7999992371,"b1eBcHjc Return Air Temperature":73.7750015259,"type":"AHU","subType":"","Status":true},"2020-04-19T09:15:00.000Z":{"dymclFPd Zone Temperature":71.6999969482,"ygZXCNrx Humidifier Valve %":0,"dECNkkkx Duct Static Pressure":0.5,"JJTf4KIN Mixed Air Temperature":67.0999984741,"ejzJNJVA TvG2WGjE Flow Setpoint":750,"QaxazYRs Pre Heating Temp":64.8000030518,"ymhl1rIT Static Pressure Setpoint":0.5,"7J5Znp6z Preheat Valve %":0,"m99GC7uz Supply Fan Output %":12.1177282333,"3p3Wd2Zp Cooling Valve %":0,"nqWMaKsU hq1bHbcu Flow":1.2620005608,"iAtum58lYXB6Es Zone Relative Humidity %":40.0999984741,"AqlRfdQi Power (Calc)":0.0285462786,"9tAKv3tG Setpoint Temperature":58,"L4Vb3H0J Schedule":0.0,"Kamr4cZz Supply Air Temperature":62.4249992371,"QNupgV5D Supply Relative Humidity Setpoint %":30,"OratacDL Supply Relative Humidity %":50.6749992371,"b1eBcHjc Return Air Temperature":73.8000030518,"type":"AHU","subType":"","Status":true},"2020-04-19T09:30:00.000Z":{"dymclFPd Zone Temperature":71.6999969482,"ygZXCNrx Humidifier Valve %":0,"dECNkkkx Duct Static Pressure":0.5,"JJTf4KIN Mixed Air Temperature":67.1750030518,"ejzJNJVA TvG2WGjE Flow Setpoint":750,"QaxazYRs Pre Heating Temp":64.3000030518,"ymhl1rIT Static Pressure Setpoint":0.5,"7J5Znp6z Preheat Valve %":0,"m99GC7uz Supply Fan Output %":12.1130027771,"3p3Wd2Zp Cooling Valve %":0,"nqWMaKsU hq1bHbcu Flow":1.4417440891,"iAtum58lYXB6Es Zone Relative Humidity %":40.2249984741,"AqlRfdQi Power (Calc)":0.0285128957,"9tAKv3tG Setpoint Temperature":58,"L4Vb3H0J Schedule":0.0,"Kamr4cZz Supply Air Temperature":62.4249992371,"QNupgV5D Supply Relative Humidity Setpoint %":30,"OratacDL Supply Relative Humidity %":50.6749992371,"b1eBcHjc Return Air Temperature":73.7249984741,"type":"AHU","subType":"","Status":true},"2020-04-19T09:45:00.000Z":{"dymclFPd Zone Temperature":71.6750030518,"ygZXCNrx Humidifier Valve %":0,"dECNkkkx Duct Static Pressure":0.5,"JJTf4KIN Mixed Air Temperature":66.5250015259,"ejzJNJVA TvG2WGjE Flow Setpoint":750,"QaxazYRs Pre Heating Temp":64.7750015259,"ymhl1rIT Static Pressure Setpoint":0.5,"7J5Znp6z Preheat Valve %":0,"m99GC7uz Supply Fan Output %":12.1199321747,"3p3Wd2Zp Cooling Valve %":0,"nqWMaKsU hq1bHbcu Flow":1.4514400959,"iAtum58lYXB6Es Zone Relative Humidity %":39.9249992371,"AqlRfdQi Power (Calc)":0.0285618572,"9tAKv3tG Setpoint Temperature":58,"L4Vb3H0J Schedule":0.0,"Kamr4cZz Supply Air Temperature":62.4249992371,"QNupgV5D Supply Relative Humidity Setpoint %":30,"OratacDL Supply Relative Humidity %":50.5750007629,"b1eBcHjc Return Air Temperature":73.75,"type":"AHU","subType":"","Status":true},"2020-04-19T10:00:00.000Z":{"dymclFPd Zone Temperature":71.6750030518,"ygZXCNrx Humidifier Valve %":0,"dECNkkkx Duct Static Pressure":0.5,"JJTf4KIN Mixed Air Temperature":67.0500030518,"ejzJNJVA TvG2WGjE Flow Setpoint":750,"QaxazYRs Pre Heating Temp":64.0749969482,"ymhl1rIT Static Pressure Setpoint":0.5,"7J5Znp6z Preheat Valve %":0,"m99GC7uz Supply Fan Output %":12.1239204407,"3p3Wd2Zp Cooling Valve %":0,"nqWMaKsU hq1bHbcu Flow":1.2997312546,"iAtum58lYXB6Es Zone Relative Humidity %":40.1500015259,"AqlRfdQi Power (Calc)":0.0285900627,"9tAKv3tG Setpoint Temperature":58,"L4Vb3H0J Schedule":0.0,"Kamr4cZz Supply Air Temperature":62.375,"QNupgV5D Supply Relative Humidity Setpoint %":30,"OratacDL Supply Relative Humidity %":50.625,"b1eBcHjc Return Air Temperature":73.7249984741,"type":"AHU","subType":"","Status":true},"2020-04-19T10:15:00.000Z":{"dymclFPd Zone Temperature":71.6750030518,"ygZXCNrx Humidifier Valve %":0,"dECNkkkx Duct Static Pressure":0.5,"JJTf4KIN Mixed Air Temperature":66.8000030518,"ejzJNJVA TvG2WGjE Flow Setpoint":750,"QaxazYRs Pre Heating Temp":64.0,"ymhl1rIT Static Pressure Setpoint":0.5,"7J5Znp6z Preheat Valve %":0,"m99GC7uz Supply Fan Output %":12.1223182678,"3p3Wd2Zp Cooling Valve %":0,"nqWMaKsU hq1bHbcu Flow":1.3858480453,"iAtum58lYXB6Es Zone Relative Humidity %":40.0999984741,"AqlRfdQi Power (Calc)":0.0285787297,"9tAKv3tG Setpoint Temperature":58,"L4Vb3H0J Schedule":0.0,"Kamr4cZz Supply Air Temperature":62.4500007629,"QNupgV5D Supply Relative Humidity Setpoint %":30,"OratacDL Supply Relative Humidity %":50.4749984741,"b1eBcHjc Return Air Temperature":73.7249984741,"type":"AHU","subType":"","Status":true},"2020-04-19T10:30:00.000Z":{"dymclFPd Zone Temperature":71.6750030518,"ygZXCNrx Humidifier Valve %":0,"dECNkkkx Duct Static Pressure":0.5,"JJTf4KIN Mixed Air Temperature":66.7750015259,"ejzJNJVA TvG2WGjE Flow Setpoint":750,"QaxazYRs Pre Heating Temp":64.4000015259,"ymhl1rIT Static Pressure Setpoint":0.5,"7J5Znp6z Preheat Valve %":0,"m99GC7uz Supply Fan Output %":12.1237010956,"3p3Wd2Zp Cooling Valve %":0,"nqWMaKsU hq1bHbcu Flow":1.3957817554,"iAtum58lYXB6Es Zone Relative Humidity %":39.9749984741,"AqlRfdQi Power (Calc)":0.028588511,"9tAKv3tG Setpoint Temperature":58,"L4Vb3H0J Schedule":0.0,"Kamr4cZz Supply Air Temperature":62.2999992371,"QNupgV5D Supply Relative Humidity Setpoint %":30,"OratacDL Supply Relative Humidity %":50.6749992371,"b1eBcHjc Return Air Temperature":73.6500015259,"type":"AHU","subType":"","Status":true},"2020-04-19T10:45:00.000Z":{"dymclFPd Zone Temperature":71.6750030518,"ygZXCNrx Humidifier Valve %":0,"dECNkkkx Duct Static Pressure":0.5,"JJTf4KIN Mixed Air Temperature":66.2750015259,"ejzJNJVA TvG2WGjE Flow Setpoint":750,"QaxazYRs Pre Heating Temp":64.6500015259,"ymhl1rIT Static Pressure Setpoint":0.5,"7J5Znp6z Preheat Valve %":0,"m99GC7uz Supply Fan Output %":12.1288146973,"3p3Wd2Zp Cooling Valve %":0,"nqWMaKsU hq1bHbcu Flow":1.4428603649,"iAtum58lYXB6Es Zone Relative Humidity %":40.2000007629,"AqlRfdQi Power (Calc)":0.0286247009,"9tAKv3tG Setpoint Temperature":58,"L4Vb3H0J Schedule":0.0,"Kamr4cZz Supply Air Temperature":62.2999992371,"QNupgV5D Supply Relative Humidity Setpoint %":30,"OratacDL Supply Relative Humidity %":50.625,"b1eBcHjc Return Air Temperature":73.6500015259,"type":"AHU","subType":"","Status":true},"2020-04-19T11:00:00.000Z":{"dymclFPd Zone Temperature":71.6750030518,"ygZXCNrx Humidifier Valve %":0,"dECNkkkx Duct Static Pressure":0.5,"JJTf4KIN Mixed Air Temperature":66.6750030518,"ejzJNJVA TvG2WGjE Flow Setpoint":750,"QaxazYRs Pre Heating Temp":64.5749969482,"ymhl1rIT Static Pressure Setpoint":0.5,"7J5Znp6z Preheat Valve %":0,"m99GC7uz Supply Fan Output %":12.1241369247,"3p3Wd2Zp Cooling Valve %":0,"nqWMaKsU hq1bHbcu Flow":1.3347862959,"iAtum58lYXB6Es Zone Relative Humidity %":40.2000007629,"AqlRfdQi Power (Calc)":0.0285915942,"9tAKv3tG Setpoint Temperature":58,"L4Vb3H0J Schedule":0.0,"Kamr4cZz Supply Air Temperature":62.2750015259,"QNupgV5D Supply Relative Humidity Setpoint %":30,"OratacDL Supply Relative Humidity %":50.75,"b1eBcHjc Return Air Temperature":73.6750030518,"type":"AHU","subType":"","Status":true},"2020-04-19T11:15:00.000Z":{"dymclFPd Zone Temperature":71.625,"ygZXCNrx Humidifier Valve %":0,"dECNkkkx Duct Static Pressure":0.5,"JJTf4KIN Mixed Air Temperature":67.5500030518,"ejzJNJVA TvG2WGjE Flow Setpoint":750,"QaxazYRs Pre Heating Temp":65.0,"ymhl1rIT Static Pressure Setpoint":0.5,"7J5Znp6z Preheat Valve %":0,"m99GC7uz Supply Fan Output %":12.1260919571,"3p3Wd2Zp Cooling Valve %":0,"nqWMaKsU hq1bHbcu Flow":1.3269791603,"iAtum58lYXB6Es Zone Relative Humidity %":40.1749992371,"AqlRfdQi Power (Calc)":0.0286054278,"9tAKv3tG Setpoint Temperature":58,"L4Vb3H0J Schedule":0.0,"Kamr4cZz Supply Air Temperature":62.2249984741,"QNupgV5D Supply Relative Humidity Setpoint %":30,"OratacDL Supply Relative Humidity %":50.8250007629,"b1eBcHjc Return Air Temperature":73.625,"type":"AHU","subType":"","Status":true},"2020-04-19T11:30:00.000Z":{"dymclFPd Zone Temperature":71.6500015259,"ygZXCNrx Humidifier Valve %":0,"dECNkkkx Duct Static Pressure":0.5,"JJTf4KIN Mixed Air Temperature":66.875,"ejzJNJVA TvG2WGjE Flow Setpoint":750,"QaxazYRs Pre Heating Temp":64.5500030518,"ymhl1rIT Static Pressure Setpoint":0.5,"7J5Znp6z Preheat Valve %":0,"m99GC7uz Supply Fan Output %":12.1103439331,"3p3Wd2Zp Cooling Valve %":0,"nqWMaKsU hq1bHbcu Flow":1.2820131779,"iAtum58lYXB6Es Zone Relative Humidity %":40.2000007629,"AqlRfdQi Power (Calc)":0.0284941238,"9tAKv3tG Setpoint Temperature":58,"L4Vb3H0J Schedule":0.0,"Kamr4cZz Supply Air Temperature":62.25,"QNupgV5D Supply Relative Humidity Setpoint %":30,"OratacDL Supply Relative Humidity %":50.8250007629,"b1eBcHjc Return Air Temperature":73.625,"type":"AHU","subType":"","Status":true},"2020-04-19T11:45:00.000Z":{"dymclFPd Zone Temperature":71.6500015259,"ygZXCNrx Humidifier Valve %":0,"dECNkkkx Duct Static Pressure":0.5,"JJTf4KIN Mixed Air Temperature":66.5999984741,"ejzJNJVA TvG2WGjE Flow Setpoint":750,"QaxazYRs Pre Heating Temp":64.2249984741,"ymhl1rIT Static Pressure Setpoint":0.5,"7J5Znp6z Preheat Valve %":0,"m99GC7uz Supply Fan Output %":12.118683815,"3p3Wd2Zp Cooling Valve %":0,"nqWMaKsU hq1bHbcu Flow":1.3622429371,"iAtum58lYXB6Es Zone Relative Humidity %":40.0,"AqlRfdQi Power (Calc)":0.0285530324,"9tAKv3tG Setpoint Temperature":58,"L4Vb3H0J Schedule":0.0,"Kamr4cZz Supply Air Temperature":62.25,"QNupgV5D Supply Relative Humidity Setpoint %":30,"OratacDL Supply Relative Humidity %":50.8499984741,"b1eBcHjc Return Air Temperature":73.625,"type":"AHU","subType":"","Status":true},"2020-04-19T12:00:00.000Z":{"dymclFPd Zone Temperature":71.625,"ygZXCNrx Humidifier Valve %":0,"dECNkkkx Duct Static Pressure":0.5,"JJTf4KIN Mixed Air Temperature":65.5500030518,"ejzJNJVA TvG2WGjE Flow Setpoint":750,"QaxazYRs Pre Heating Temp":63.9500007629,"ymhl1rIT Static Pressure Setpoint":0.5,"7J5Znp6z Preheat Valve %":0,"m99GC7uz Supply Fan Output %":12.1214599609,"3p3Wd2Zp Cooling Valve %":0,"nqWMaKsU hq1bHbcu Flow":1.4430621862,"iAtum58lYXB6Es Zone Relative Humidity %":40.0499992371,"AqlRfdQi Power (Calc)":0.0285726597,"9tAKv3tG Setpoint Temperature":58,"L4Vb3H0J Schedule":0.0,"Kamr4cZz Supply Air Temperature":62.2249984741,"QNupgV5D Supply Relative Humidity Setpoint %":30,"OratacDL Supply Relative Humidity %":50.875,"b1eBcHjc Return Air Temperature":73.625,"type":"AHU","subType":"","Status":true},"2020-04-19T12:15:00.000Z":{"dymclFPd Zone Temperature":71.625,"ygZXCNrx Humidifier Valve %":0,"dECNkkkx Duct Static Pressure":0.5,"JJTf4KIN Mixed Air Temperature":67.1999969482,"ejzJNJVA TvG2WGjE Flow Setpoint":750,"QaxazYRs Pre Heating Temp":64.9499969482,"ymhl1rIT Static Pressure Setpoint":0.5,"7J5Znp6z Preheat Valve %":0,"m99GC7uz Supply Fan Output %":12.1143817902,"3p3Wd2Zp Cooling Valve %":0,"nqWMaKsU hq1bHbcu Flow":1.3958684206,"iAtum58lYXB6Es Zone Relative Humidity %":39.9249992371,"AqlRfdQi Power (Calc)":0.028522635,"9tAKv3tG Setpoint Temperature":58,"L4Vb3H0J Schedule":0.0,"Kamr4cZz Supply Air Temperature":62.25,"QNupgV5D Supply Relative Humidity Setpoint %":30,"OratacDL Supply Relative Humidity %":50.8250007629,"b1eBcHjc Return Air Temperature":73.5749969482,"type":"AHU","subType":"","Status":true},"2020-04-19T12:30:00.000Z":{"dymclFPd Zone Temperature":71.5999984741,"ygZXCNrx Humidifier Valve %":0,"dECNkkkx Duct Static Pressure":0.5,"JJTf4KIN Mixed Air Temperature":66.0749969482,"ejzJNJVA TvG2WGjE Flow Setpoint":750,"QaxazYRs Pre Heating Temp":63.5,"ymhl1rIT Static Pressure Setpoint":0.5,"7J5Znp6z Preheat Valve %":0,"m99GC7uz Supply Fan Output %":12.1242723465,"3p3Wd2Zp Cooling Valve %":0,"nqWMaKsU hq1bHbcu Flow":1.4125862122,"iAtum58lYXB6Es Zone Relative Humidity %":40.0750007629,"AqlRfdQi Power (Calc)":0.0285925523,"9tAKv3tG Setpoint Temperature":58,"L4Vb3H0J Schedule":0.0,"Kamr4cZz Supply Air Temperature":62.25,"QNupgV5D Supply Relative Humidity Setpoint %":30,"OratacDL Supply Relative Humidity %":50.7999992371,"b1eBcHjc Return Air Temperature":73.625,"type":"AHU","subType":"","Status":true},"2020-04-19T12:45:00.000Z":{"dymclFPd Zone Temperature":71.5749969482,"ygZXCNrx Humidifier Valve %":0,"dECNkkkx Duct Static Pressure":0.5,"JJTf4KIN Mixed Air Temperature":66.75,"ejzJNJVA TvG2WGjE Flow Setpoint":750,"QaxazYRs Pre Heating Temp":64.9000015259,"ymhl1rIT Static Pressure Setpoint":0.5,"7J5Znp6z Preheat Valve %":0,"m99GC7uz Supply Fan Output %":12.1236057281,"3p3Wd2Zp Cooling Valve %":0,"nqWMaKsU hq1bHbcu Flow":1.3931154013,"iAtum58lYXB6Es Zone Relative Humidity %":40.0999984741,"AqlRfdQi Power (Calc)":0.0285878363,"9tAKv3tG Setpoint Temperature":58,"L4Vb3H0J Schedule":0.0,"Kamr4cZz Supply Air Temperature":62.8250007629,"QNupgV5D Supply Relative Humidity Setpoint %":30,"OratacDL Supply Relative Humidity %":49.7249984741,"b1eBcHjc Return Air Temperature":73.5749969482,"type":"AHU","subType":"","Status":true},"2020-04-19T13:00:00.000Z":{"dymclFPd Zone Temperature":71.5749969482,"ygZXCNrx Humidifier Valve %":0,"dECNkkkx Duct Static Pressure":0.5,"JJTf4KIN Mixed Air Temperature":66.6999969482,"ejzJNJVA TvG2WGjE Flow Setpoint":750,"QaxazYRs Pre Heating Temp":64.75,"ymhl1rIT Static Pressure Setpoint":0.5,"7J5Znp6z Preheat Valve %":0,"m99GC7uz Supply Fan Output %":12.1790819168,"3p3Wd2Zp Cooling Valve %":0,"nqWMaKsU hq1bHbcu Flow":1.3727207184,"iAtum58lYXB6Es Zone Relative Humidity %":40.125,"AqlRfdQi Power (Calc)":0.0289820786,"9tAKv3tG Setpoint Temperature":58,"L4Vb3H0J Schedule":0.0,"Kamr4cZz Supply Air Temperature":63.5999984741,"QNupgV5D Supply Relative Humidity Setpoint %":30,"OratacDL Supply Relative Humidity %":48.4749984741,"b1eBcHjc Return Air Temperature":73.5749969482,"type":"AHU","subType":"","Status":true},"2020-04-19T13:15:00.000Z":{"dymclFPd Zone Temperature":71.5500030518,"ygZXCNrx Humidifier Valve %":0,"dECNkkkx Duct Static Pressure":0.5,"JJTf4KIN Mixed Air Temperature":67.1500015259,"ejzJNJVA TvG2WGjE Flow Setpoint":750,"QaxazYRs Pre Heating Temp":65.0749969482,"ymhl1rIT Static Pressure Setpoint":0.5,"7J5Znp6z Preheat Valve %":0,"m99GC7uz Supply Fan Output %":12.1836452484,"3p3Wd2Zp Cooling Valve %":0,"nqWMaKsU hq1bHbcu Flow":1.3764036894,"iAtum58lYXB6Es Zone Relative Humidity %":40.2999992371,"AqlRfdQi Power (Calc)":0.0290146683,"9tAKv3tG Setpoint Temperature":58,"L4Vb3H0J Schedule":0.0,"Kamr4cZz Supply Air Temperature":63.6749992371,"QNupgV5D Supply Relative Humidity Setpoint %":30,"OratacDL Supply Relative Humidity %":48.2999992371,"b1eBcHjc Return Air Temperature":73.5749969482,"type":"AHU","subType":"","Status":true},"2020-04-19T13:30:00.000Z":{"dymclFPd Zone Temperature":71.5749969482,"ygZXCNrx Humidifier Valve %":0,"dECNkkkx Duct Static Pressure":0.5,"JJTf4KIN Mixed Air Temperature":66.625,"ejzJNJVA TvG2WGjE Flow Setpoint":750,"QaxazYRs Pre Heating Temp":64.5,"ymhl1rIT Static Pressure Setpoint":0.5,"7J5Znp6z Preheat Valve %":0,"m99GC7uz Supply Fan Output %":12.1860189438,"3p3Wd2Zp Cooling Valve %":0,"nqWMaKsU hq1bHbcu Flow":1.4932671785,"iAtum58lYXB6Es Zone Relative Humidity %":40.2000007629,"AqlRfdQi Power (Calc)":0.0290316301,"9tAKv3tG Setpoint Temperature":58,"L4Vb3H0J Schedule":0.0,"Kamr4cZz Supply Air Temperature":63.6500015259,"QNupgV5D Supply Relative Humidity Setpoint %":30,"OratacDL Supply Relative Humidity %":48.25,"b1eBcHjc Return Air Temperature":73.5749969482,"type":"AHU","subType":"","Status":true},"2020-04-19T13:45:00.000Z":{"dymclFPd Zone Temperature":71.5749969482,"ygZXCNrx Humidifier Valve %":0,"dECNkkkx Duct Static Pressure":0.5,"JJTf4KIN Mixed Air Temperature":66.6999969482,"ejzJNJVA TvG2WGjE Flow Setpoint":750,"QaxazYRs Pre Heating Temp":64.2750015259,"ymhl1rIT Static Pressure Setpoint":0.5,"7J5Znp6z Preheat Valve %":0,"m99GC7uz Supply Fan Output %":12.1939287186,"3p3Wd2Zp Cooling Valve %":0,"nqWMaKsU hq1bHbcu Flow":1.2887238264,"iAtum58lYXB6Es Zone Relative Humidity %":40.0499992371,"AqlRfdQi Power (Calc)":0.0290881989,"9tAKv3tG Setpoint Temperature":58,"L4Vb3H0J Schedule":0.0,"Kamr4cZz Supply Air Temperature":63.7000007629,"QNupgV5D Supply Relative Humidity Setpoint %":30,"OratacDL Supply Relative Humidity %":48.2249984741,"b1eBcHjc Return Air Temperature":73.5749969482,"type":"AHU","subType":"","Status":true},"2020-04-19T14:00:00.000Z":{"dymclFPd Zone Temperature":71.5749969482,"ygZXCNrx Humidifier Valve %":0,"dECNkkkx Duct Static Pressure":0.5,"JJTf4KIN Mixed Air Temperature":66.0999984741,"ejzJNJVA TvG2WGjE Flow Setpoint":750,"QaxazYRs Pre Heating Temp":64.5999984741,"ymhl1rIT Static Pressure Setpoint":0.5,"7J5Znp6z Preheat Valve %":0,"m99GC7uz Supply Fan Output %":12.1992378235,"3p3Wd2Zp Cooling Valve %":0,"nqWMaKsU hq1bHbcu Flow":1.3589730263,"iAtum58lYXB6Es Zone Relative Humidity %":40.0250015259,"AqlRfdQi Power (Calc)":0.0291262095,"9tAKv3tG Setpoint Temperature":58,"L4Vb3H0J Schedule":0.0,"Kamr4cZz Supply Air Temperature":63.6749992371,"QNupgV5D Supply Relative Humidity Setpoint %":30,"OratacDL Supply Relative Humidity %":48.1500015259,"b1eBcHjc Return Air Temperature":73.5999984741,"type":"AHU","subType":"","Status":true},"2020-04-19T14:15:00.000Z":{"dymclFPd Zone Temperature":71.5999984741,"ygZXCNrx Humidifier Valve %":0,"dECNkkkx Duct Static Pressure":0.5,"JJTf4KIN Mixed Air Temperature":66.9000015259,"ejzJNJVA TvG2WGjE Flow Setpoint":750,"QaxazYRs Pre Heating Temp":64.9749984741,"ymhl1rIT Static Pressure Setpoint":0.5,"7J5Znp6z Preheat Valve %":0,"m99GC7uz Supply Fan Output %":12.2033185959,"3p3Wd2Zp Cooling Valve %":0,"nqWMaKsU hq1bHbcu Flow":1.3438508511,"iAtum58lYXB6Es Zone Relative Humidity %":40.0750007629,"AqlRfdQi Power (Calc)":0.0291554483,"9tAKv3tG Setpoint Temperature":58,"L4Vb3H0J Schedule":0.0,"Kamr4cZz Supply Air Temperature":63.7000007629,"QNupgV5D Supply Relative Humidity Setpoint %":30,"OratacDL Supply Relative Humidity %":48.125,"b1eBcHjc Return Air Temperature":73.625,"type":"AHU","subType":"","Status":true},"2020-04-19T14:30:00.000Z":{"dymclFPd Zone Temperature":71.5999984741,"ygZXCNrx Humidifier Valve %":0,"dECNkkkx Duct Static Pressure":0.5,"JJTf4KIN Mixed Air Temperature":66.6750030518,"ejzJNJVA TvG2WGjE Flow Setpoint":750,"QaxazYRs Pre Heating Temp":65.0749969482,"ymhl1rIT Static Pressure Setpoint":0.5,"7J5Znp6z Preheat Valve %":0,"m99GC7uz Supply Fan Output %":12.2733221054,"3p3Wd2Zp Cooling Valve %":0,"nqWMaKsU hq1bHbcu Flow":1.3908240795,"iAtum58lYXB6Es Zone Relative Humidity %":39.9749984741,"AqlRfdQi Power (Calc)":0.0296600768,"9tAKv3tG Setpoint Temperature":58,"L4Vb3H0J Schedule":0.0,"Kamr4cZz Supply Air Temperature":63.7249984741,"QNupgV5D Supply Relative Humidity Setpoint %":30,"OratacDL Supply Relative Humidity %":48.0999984741,"b1eBcHjc Return Air Temperature":73.6500015259,"type":"AHU","subType":"","Status":true},"2020-04-19T14:45:00.000Z":{"dymclFPd Zone Temperature":71.6500015259,"ygZXCNrx Humidifier Valve %":0,"dECNkkkx Duct Static Pressure":0.5,"JJTf4KIN Mixed Air Temperature":67.5749969482,"ejzJNJVA TvG2WGjE Flow Setpoint":750,"QaxazYRs Pre Heating Temp":65.6500015259,"ymhl1rIT Static Pressure Setpoint":0.5,"7J5Znp6z Preheat Valve %":0,"m99GC7uz Supply Fan Output %":12.2877836227,"3p3Wd2Zp Cooling Valve %":0,"nqWMaKsU hq1bHbcu Flow":1.2808771133,"iAtum58lYXB6Es Zone Relative Humidity %":40.0,"AqlRfdQi Power (Calc)":0.0297650448,"9tAKv3tG Setpoint Temperature":58,"L4Vb3H0J Schedule":0.0,"Kamr4cZz Supply Air Temperature":63.75,"QNupgV5D Supply Relative Humidity Setpoint %":30,"OratacDL Supply Relative Humidity %":47.9749984741,"b1eBcHjc Return Air Temperature":73.6999969482,"type":"AHU","subType":"","Status":true},"2020-04-19T15:00:00.000Z":{"dymclFPd Zone Temperature":71.6500015259,"ygZXCNrx Humidifier Valve %":0,"dECNkkkx Duct Static Pressure":0.5,"JJTf4KIN Mixed Air Temperature":66.7750015259,"ejzJNJVA TvG2WGjE Flow Setpoint":750,"QaxazYRs Pre Heating Temp":64.875,"ymhl1rIT Static Pressure Setpoint":0.5,"7J5Znp6z Preheat Valve %":0,"m99GC7uz Supply Fan Output %":12.2815742493,"3p3Wd2Zp Cooling Valve %":0,"nqWMaKsU hq1bHbcu Flow":1.3528674841,"iAtum58lYXB6Es Zone Relative Humidity %":40.0250015259,"AqlRfdQi Power (Calc)":0.0297199442,"9tAKv3tG Setpoint Temperature":58,"L4Vb3H0J Schedule":0.0,"Kamr4cZz Supply Air Temperature":63.7750015259,"QNupgV5D Supply Relative Humidity Setpoint %":30,"OratacDL Supply Relative Humidity %":47.9749984741,"b1eBcHjc Return Air Temperature":73.6999969482,"type":"AHU","subType":"","Status":true},"2020-04-19T15:15:00.000Z":{"dymclFPd Zone Temperature":71.6750030518,"ygZXCNrx Humidifier Valve %":0,"dECNkkkx Duct Static Pressure":0.5,"JJTf4KIN Mixed Air Temperature":67.1999969482,"ejzJNJVA TvG2WGjE Flow Setpoint":750,"QaxazYRs Pre Heating Temp":64.9000015259,"ymhl1rIT Static Pressure Setpoint":0.5,"7J5Znp6z Preheat Valve %":0,"m99GC7uz Supply Fan Output %":12.2901744843,"3p3Wd2Zp Cooling Valve %":0,"nqWMaKsU hq1bHbcu Flow":1.4290297031,"iAtum58lYXB6Es Zone Relative Humidity %":39.9500007629,"AqlRfdQi Power (Calc)":0.0297824225,"9tAKv3tG Setpoint Temperature":58,"L4Vb3H0J Schedule":0.0,"Kamr4cZz Supply Air Temperature":63.7999992371,"QNupgV5D Supply Relative Humidity Setpoint %":30,"OratacDL Supply Relative Humidity %":47.9500007629,"b1eBcHjc Return Air Temperature":73.7249984741,"type":"AHU","subType":"","Status":true},"2020-04-19T15:30:00.000Z":{"dymclFPd Zone Temperature":71.6999969482,"ygZXCNrx Humidifier Valve %":0,"dECNkkkx Duct Static Pressure":0.5,"JJTf4KIN Mixed Air Temperature":66.9499969482,"ejzJNJVA TvG2WGjE Flow Setpoint":750,"QaxazYRs Pre Heating Temp":64.8249969482,"ymhl1rIT Static Pressure Setpoint":0.5,"7J5Znp6z Preheat Valve %":0,"m99GC7uz Supply Fan Output %":12.3167533875,"3p3Wd2Zp Cooling Valve %":0,"nqWMaKsU hq1bHbcu Flow":1.3173203468,"iAtum58lYXB6Es Zone Relative Humidity %":40.1500015259,"AqlRfdQi Power (Calc)":0.0299760643,"9tAKv3tG Setpoint Temperature":58,"L4Vb3H0J Schedule":0.0,"Kamr4cZz Supply Air Temperature":63.7999992371,"QNupgV5D Supply Relative Humidity Setpoint %":30,"OratacDL Supply Relative Humidity %":48.0250015259,"b1eBcHjc Return Air Temperature":73.8000030518,"type":"AHU","subType":"","Status":true},"2020-04-19T15:45:00.000Z":{"dymclFPd Zone Temperature":71.7249984741,"ygZXCNrx Humidifier Valve %":0,"dECNkkkx Duct Static Pressure":0.5,"JJTf4KIN Mixed Air Temperature":67.4250030518,"ejzJNJVA TvG2WGjE Flow Setpoint":750,"QaxazYRs Pre Heating Temp":65.7249984741,"ymhl1rIT Static Pressure Setpoint":0.5,"7J5Znp6z Preheat Valve %":0,"m99GC7uz Supply Fan Output %":12.2655286789,"3p3Wd2Zp Cooling Valve %":0,"nqWMaKsU hq1bHbcu Flow":1.3510724306,"iAtum58lYXB6Es Zone Relative Humidity %":40.0,"AqlRfdQi Power (Calc)":0.0296036112,"9tAKv3tG Setpoint Temperature":58,"L4Vb3H0J Schedule":0.0,"Kamr4cZz Supply Air Temperature":61.6500015259,"QNupgV5D Supply Relative Humidity Setpoint %":30,"OratacDL Supply Relative Humidity %":51.7249984741,"b1eBcHjc Return Air Temperature":73.75,"type":"AHU","subType":"","Status":true},"2020-04-19T16:00:00.000Z":{"dymclFPd Zone Temperature":71.75,"ygZXCNrx Humidifier Valve %":0,"dECNkkkx Duct Static Pressure":0.5,"JJTf4KIN Mixed Air Temperature":66.5999984741,"ejzJNJVA TvG2WGjE Flow Setpoint":750,"QaxazYRs Pre Heating Temp":64.75,"ymhl1rIT Static Pressure Setpoint":0.5,"7J5Znp6z Preheat Valve %":0,"m99GC7uz Supply Fan Output %":12.2654180527,"3p3Wd2Zp Cooling Valve %":0,"nqWMaKsU hq1bHbcu Flow":1.4156658649,"iAtum58lYXB6Es Zone Relative Humidity %":40.1749992371,"AqlRfdQi Power (Calc)":0.0296028102,"9tAKv3tG Setpoint Temperature":58,"L4Vb3H0J Schedule":0.0,"Kamr4cZz Supply Air Temperature":61.5499992371,"QNupgV5D Supply Relative Humidity Setpoint %":30,"OratacDL Supply Relative Humidity %":51.9500007629,"b1eBcHjc Return Air Temperature":73.8000030518,"type":"AHU","subType":"","Status":true},"2020-04-19T16:15:00.000Z":{"dymclFPd Zone Temperature":71.75,"ygZXCNrx Humidifier Valve %":0,"dECNkkkx Duct Static Pressure":0.5,"JJTf4KIN Mixed Air Temperature":67.0250015259,"ejzJNJVA TvG2WGjE Flow Setpoint":750,"QaxazYRs Pre Heating Temp":64.3499984741,"ymhl1rIT Static Pressure Setpoint":0.5,"7J5Znp6z Preheat Valve %":0,"m99GC7uz Supply Fan Output %":12.2538042068,"3p3Wd2Zp Cooling Valve %":0,"nqWMaKsU hq1bHbcu Flow":1.4692651033,"iAtum58lYXB6Es Zone Relative Humidity %":40.2999992371,"AqlRfdQi Power (Calc)":0.0295187991,"9tAKv3tG Setpoint Temperature":58,"L4Vb3H0J Schedule":0.0,"Kamr4cZz Supply Air Temperature":61.5499992371,"QNupgV5D Supply Relative Humidity Setpoint %":30,"OratacDL Supply Relative Humidity %":51.9500007629,"b1eBcHjc Return Air Temperature":73.8249969482,"type":"AHU","subType":"","Status":true},"2020-04-19T16:30:00.000Z":{"dymclFPd Zone Temperature":71.75,"ygZXCNrx Humidifier Valve %":0,"dECNkkkx Duct Static Pressure":0.5,"JJTf4KIN Mixed Air Temperature":67.9749984741,"ejzJNJVA TvG2WGjE Flow Setpoint":750,"QaxazYRs Pre Heating Temp":65.3249969482,"ymhl1rIT Static Pressure Setpoint":0.5,"7J5Znp6z Preheat Valve %":0,"m99GC7uz Supply Fan Output %":12.2535419464,"3p3Wd2Zp Cooling Valve %":0,"nqWMaKsU hq1bHbcu Flow":1.4258788824,"iAtum58lYXB6Es Zone Relative Humidity %":40.0750007629,"AqlRfdQi Power (Calc)":0.0295169038,"9tAKv3tG Setpoint Temperature":58,"L4Vb3H0J Schedule":0.0,"Kamr4cZz Supply Air Temperature":61.6500015259,"QNupgV5D Supply Relative Humidity Setpoint %":30,"OratacDL Supply Relative Humidity %":51.9000015259,"b1eBcHjc Return Air Temperature":73.9499969482,"type":"AHU","subType":"","Status":true},"2020-04-19T16:45:00.000Z":{"dymclFPd Zone Temperature":71.7249984741,"ygZXCNrx Humidifier Valve %":0,"dECNkkkx Duct Static Pressure":0.5,"JJTf4KIN Mixed Air Temperature":68.0500030518,"ejzJNJVA TvG2WGjE Flow Setpoint":750,"QaxazYRs Pre Heating Temp":65.9749984741,"ymhl1rIT Static Pressure Setpoint":0.5,"7J5Znp6z Preheat Valve %":0,"m99GC7uz Supply Fan Output %":12.2373008728,"3p3Wd2Zp Cooling Valve %":0,"nqWMaKsU hq1bHbcu Flow":1.4384617805,"iAtum58lYXB6Es Zone Relative Humidity %":39.9749984741,"AqlRfdQi Power (Calc)":0.0293996925,"9tAKv3tG Setpoint Temperature":58,"L4Vb3H0J Schedule":0.0,"Kamr4cZz Supply Air Temperature":61.625,"QNupgV5D Supply Relative Humidity Setpoint %":30,"OratacDL Supply Relative Humidity %":52.0250015259,"b1eBcHjc Return Air Temperature":73.9749984741,"type":"AHU","subType":"","Status":true},"2020-04-19T17:00:00.000Z":{"dymclFPd Zone Temperature":71.6999969482,"ygZXCNrx Humidifier Valve %":0,"dECNkkkx Duct Static Pressure":0.5,"JJTf4KIN Mixed Air Temperature":67.1500015259,"ejzJNJVA TvG2WGjE Flow Setpoint":750,"QaxazYRs Pre Heating Temp":65.1500015259,"ymhl1rIT Static Pressure Setpoint":0.5,"7J5Znp6z Preheat Valve %":0,"m99GC7uz Supply Fan Output %":12.2520284653,"3p3Wd2Zp Cooling Valve %":0,"nqWMaKsU hq1bHbcu Flow":1.3968553543,"iAtum58lYXB6Es Zone Relative Humidity %":40.1749992371,"AqlRfdQi Power (Calc)":0.0295059679,"9tAKv3tG Setpoint Temperature":58,"L4Vb3H0J Schedule":0.0,"Kamr4cZz Supply Air Temperature":61.625,"QNupgV5D Supply Relative Humidity Setpoint %":30,"OratacDL Supply Relative Humidity %":52.0250015259,"b1eBcHjc Return Air Temperature":74.0749969482,"type":"AHU","subType":"","Status":true},"2020-04-19T17:15:00.000Z":{"dymclFPd Zone Temperature":71.6999969482,"ygZXCNrx Humidifier Valve %":0,"dECNkkkx Duct Static Pressure":0.5,"JJTf4KIN Mixed Air Temperature":68.3000030518,"ejzJNJVA TvG2WGjE Flow Setpoint":750,"QaxazYRs Pre Heating Temp":65.9000015259,"ymhl1rIT Static Pressure Setpoint":0.5,"7J5Znp6z Preheat Valve %":0,"m99GC7uz Supply Fan Output %":12.2801685333,"3p3Wd2Zp Cooling Valve %":0,"nqWMaKsU hq1bHbcu Flow":1.4693001509,"iAtum58lYXB6Es Zone Relative Humidity %":40.0250015259,"AqlRfdQi Power (Calc)":0.0297097403,"9tAKv3tG Setpoint Temperature":58,"L4Vb3H0J Schedule":0.0,"Kamr4cZz Supply Air Temperature":61.7000007629,"QNupgV5D Supply Relative Humidity Setpoint %":30,"OratacDL Supply Relative Humidity %":52.0250015259,"b1eBcHjc Return Air Temperature":74.125,"type":"AHU","subType":"","Status":true},"2020-04-19T17:30:00.000Z":{"dymclFPd Zone Temperature":71.6999969482,"ygZXCNrx Humidifier Valve %":0,"dECNkkkx Duct Static Pressure":0.5,"JJTf4KIN Mixed Air Temperature":68.0749969482,"ejzJNJVA TvG2WGjE Flow Setpoint":750,"QaxazYRs Pre Heating Temp":65.3000030518,"ymhl1rIT Static Pressure Setpoint":0.5,"7J5Znp6z Preheat Valve %":0,"m99GC7uz Supply Fan Output %":12.2838134766,"3p3Wd2Zp Cooling Valve %":0,"nqWMaKsU hq1bHbcu Flow":1.2865374088,"iAtum58lYXB6Es Zone Relative Humidity %":40.0499992371,"AqlRfdQi Power (Calc)":0.0297362031,"9tAKv3tG Setpoint Temperature":58,"L4Vb3H0J Schedule":0.0,"Kamr4cZz Supply Air Temperature":61.7249984741,"QNupgV5D Supply Relative Humidity Setpoint %":30,"OratacDL Supply Relative Humidity %":52.0499992371,"b1eBcHjc Return Air Temperature":74.1999969482,"type":"AHU","subType":"","Status":true},"2020-04-19T17:45:00.000Z":{"dymclFPd Zone Temperature":71.6999969482,"ygZXCNrx Humidifier Valve %":0,"dECNkkkx Duct Static Pressure":0.5,"JJTf4KIN Mixed Air Temperature":68.3000030518,"ejzJNJVA TvG2WGjE Flow Setpoint":750,"QaxazYRs Pre Heating Temp":65.6999969482,"ymhl1rIT Static Pressure Setpoint":0.5,"7J5Znp6z Preheat Valve %":0,"m99GC7uz Supply Fan Output %":12.2791509628,"3p3Wd2Zp Cooling Valve %":0,"nqWMaKsU hq1bHbcu Flow":1.4544405937,"iAtum58lYXB6Es Zone Relative Humidity %":40.1500015259,"AqlRfdQi Power (Calc)":0.0297023554,"9tAKv3tG Setpoint Temperature":58,"L4Vb3H0J Schedule":0.0,"Kamr4cZz Supply Air Temperature":61.75,"QNupgV5D Supply Relative Humidity Setpoint %":30,"OratacDL Supply Relative Humidity %":52.0999984741,"b1eBcHjc Return Air Temperature":74.25,"type":"AHU","subType":"","Status":true},"2020-04-19T18:00:00.000Z":{"dymclFPd Zone Temperature":71.6750030518,"ygZXCNrx Humidifier Valve %":0,"dECNkkkx Duct Static Pressure":0.5,"JJTf4KIN Mixed Air Temperature":68.5,"ejzJNJVA TvG2WGjE Flow Setpoint":750,"QaxazYRs Pre Heating Temp":66.3249969482,"ymhl1rIT Static Pressure Setpoint":0.5,"7J5Znp6z Preheat Valve %":0,"m99GC7uz Supply Fan Output %":12.2876558304,"3p3Wd2Zp Cooling Valve %":0,"nqWMaKsU hq1bHbcu Flow":1.3993918896,"iAtum58lYXB6Es Zone Relative Humidity %":40.2750015259,"AqlRfdQi Power (Calc)":0.0297641161,"9tAKv3tG Setpoint Temperature":58,"L4Vb3H0J Schedule":0.0,"Kamr4cZz Supply Air Temperature":61.9500007629,"QNupgV5D Supply Relative Humidity Setpoint %":30,"OratacDL Supply Relative Humidity %":51.6749992371,"b1eBcHjc Return Air Temperature":74.25,"type":"AHU","subType":"","Status":true},"2020-04-19T18:15:00.000Z":{"dymclFPd Zone Temperature":71.6999969482,"ygZXCNrx Humidifier Valve %":0,"dECNkkkx Duct Static Pressure":0.5,"JJTf4KIN Mixed Air Temperature":68.5999984741,"ejzJNJVA TvG2WGjE Flow Setpoint":750,"QaxazYRs Pre Heating Temp":66.4749984741,"ymhl1rIT Static Pressure Setpoint":0.5,"7J5Znp6z Preheat Valve %":0,"m99GC7uz Supply Fan Output %":12.2903623581,"3p3Wd2Zp Cooling Valve %":0,"nqWMaKsU hq1bHbcu Flow":1.3782676458,"iAtum58lYXB6Es Zone Relative Humidity %":40.25,"AqlRfdQi Power (Calc)":0.0297837883,"9tAKv3tG Setpoint Temperature":58,"L4Vb3H0J Schedule":0.0,"Kamr4cZz Supply Air Temperature":62.5250015259,"QNupgV5D Supply Relative Humidity Setpoint %":30,"OratacDL Supply Relative Humidity %":50.7249984741,"b1eBcHjc Return Air Temperature":74.3499984741,"type":"AHU","subType":"","Status":true},"2020-04-19T18:30:00.000Z":{"dymclFPd Zone Temperature":71.6999969482,"ygZXCNrx Humidifier Valve %":0,"dECNkkkx Duct Static Pressure":0.5,"JJTf4KIN Mixed Air Temperature":68.8249969482,"ejzJNJVA TvG2WGjE Flow Setpoint":750,"QaxazYRs Pre Heating Temp":66.4749984741,"ymhl1rIT Static Pressure Setpoint":0.5,"7J5Znp6z Preheat Valve %":0,"m99GC7uz Supply Fan Output %":12.3265037537,"3p3Wd2Zp Cooling Valve %":0,"nqWMaKsU hq1bHbcu Flow":1.3509345055,"iAtum58lYXB6Es Zone Relative Humidity %":40.2000007629,"AqlRfdQi Power (Calc)":0.030047311,"9tAKv3tG Setpoint Temperature":58,"L4Vb3H0J Schedule":0.0,"Kamr4cZz Supply Air Temperature":62.9500007629,"QNupgV5D Supply Relative Humidity Setpoint %":30,"OratacDL Supply Relative Humidity %":50.0499992371,"b1eBcHjc Return Air Temperature":74.4250030518,"type":"AHU","subType":"","Status":true},"2020-04-19T18:45:00.000Z":{"dymclFPd Zone Temperature":71.75,"ygZXCNrx Humidifier Valve %":0,"dECNkkkx Duct Static Pressure":0.5,"JJTf4KIN Mixed Air Temperature":68.375,"ejzJNJVA TvG2WGjE Flow Setpoint":750,"QaxazYRs Pre Heating Temp":66.6999969482,"ymhl1rIT Static Pressure Setpoint":0.5,"7J5Znp6z Preheat Valve %":0,"m99GC7uz Supply Fan Output %":12.3378868103,"3p3Wd2Zp Cooling Valve %":0,"nqWMaKsU hq1bHbcu Flow":1.3126530647,"iAtum58lYXB6Es Zone Relative Humidity %":40.2249984741,"AqlRfdQi Power (Calc)":0.0301306305,"9tAKv3tG Setpoint Temperature":58,"L4Vb3H0J Schedule":0.0,"Kamr4cZz Supply Air Temperature":63.0750007629,"QNupgV5D Supply Relative Humidity Setpoint %":30,"OratacDL Supply Relative Humidity %":49.9000015259,"b1eBcHjc Return Air Temperature":74.5,"type":"AHU","subType":"","Status":true},"2020-04-19T19:00:00.000Z":{"dymclFPd Zone Temperature":71.75,"ygZXCNrx Humidifier Valve %":0,"dECNkkkx Duct Static Pressure":0.5,"JJTf4KIN Mixed Air Temperature":68.5999984741,"ejzJNJVA TvG2WGjE Flow Setpoint":750,"QaxazYRs Pre Heating Temp":66.4250030518,"ymhl1rIT Static Pressure Setpoint":0.5,"7J5Znp6z Preheat Valve %":0,"m99GC7uz Supply Fan Output %":12.3876609802,"3p3Wd2Zp Cooling Valve %":0,"nqWMaKsU hq1bHbcu Flow":1.4229574203,"iAtum58lYXB6Es Zone Relative Humidity %":40.125,"AqlRfdQi Power (Calc)":0.0304967675,"9tAKv3tG Setpoint Temperature":58,"L4Vb3H0J Schedule":0.0,"Kamr4cZz Supply Air Temperature":63.125,"QNupgV5D Supply Relative Humidity Setpoint %":30,"OratacDL Supply Relative Humidity %":49.8499984741,"b1eBcHjc Return Air Temperature":74.5749969482,"type":"AHU","subType":"","Status":true},"2020-04-19T19:15:00.000Z":{"dymclFPd Zone Temperature":71.7750015259,"ygZXCNrx Humidifier Valve %":0,"dECNkkkx Duct Static Pressure":0.5,"JJTf4KIN Mixed Air Temperature":68.6750030518,"ejzJNJVA TvG2WGjE Flow Setpoint":750,"QaxazYRs Pre Heating Temp":66.5500030518,"ymhl1rIT Static Pressure Setpoint":0.5,"7J5Znp6z Preheat Valve %":0,"m99GC7uz Supply Fan Output %":12.4195480347,"3p3Wd2Zp Cooling Valve %":0,"nqWMaKsU hq1bHbcu Flow":1.4047371149,"iAtum58lYXB6Es Zone Relative Humidity %":40.2750015259,"AqlRfdQi Power (Calc)":0.0307328792,"9tAKv3tG Setpoint Temperature":58,"L4Vb3H0J Schedule":0.0,"Kamr4cZz Supply Air Temperature":63.2000007629,"QNupgV5D Supply Relative Humidity Setpoint %":30,"OratacDL Supply Relative Humidity %":49.75,"b1eBcHjc Return Air Temperature":74.625,"type":"AHU","subType":"","Status":true},"2020-04-19T19:30:00.000Z":{"dymclFPd Zone Temperature":71.8000030518,"ygZXCNrx Humidifier Valve %":0,"dECNkkkx Duct Static Pressure":0.5,"JJTf4KIN Mixed Air Temperature":68.5250015259,"ejzJNJVA TvG2WGjE Flow Setpoint":750,"QaxazYRs Pre Heating Temp":66.75,"ymhl1rIT Static Pressure Setpoint":0.5,"7J5Znp6z Preheat Valve %":0,"m99GC7uz Supply Fan Output %":12.4194164276,"3p3Wd2Zp Cooling Valve %":0,"nqWMaKsU hq1bHbcu Flow":1.3625196218,"iAtum58lYXB6Es Zone Relative Humidity %":40.25,"AqlRfdQi Power (Calc)":0.0307319022,"9tAKv3tG Setpoint Temperature":58,"L4Vb3H0J Schedule":0.0,"Kamr4cZz Supply Air Temperature":63.25,"QNupgV5D Supply Relative Humidity Setpoint %":30,"OratacDL Supply Relative Humidity %":49.6749992371,"b1eBcHjc Return Air Temperature":74.7249984741,"type":"AHU","subType":"","Status":true},"2020-04-19T19:45:00.000Z":{"dymclFPd Zone Temperature":71.8499984741,"ygZXCNrx Humidifier Valve %":0,"dECNkkkx Duct Static Pressure":0.5,"JJTf4KIN Mixed Air Temperature":67.875,"ejzJNJVA TvG2WGjE Flow Setpoint":750,"QaxazYRs Pre Heating Temp":66.3499984741,"ymhl1rIT Static Pressure Setpoint":0.5,"7J5Znp6z Preheat Valve %":0,"m99GC7uz Supply Fan Output %":12.4868927002,"3p3Wd2Zp Cooling Valve %":0,"nqWMaKsU hq1bHbcu Flow":1.3345216513,"iAtum58lYXB6Es Zone Relative Humidity %":40.0,"AqlRfdQi Power (Calc)":0.0312355397,"9tAKv3tG Setpoint Temperature":58,"L4Vb3H0J Schedule":0.0,"Kamr4cZz Supply Air Temperature":63.25,"QNupgV5D Supply Relative Humidity Setpoint %":30,"OratacDL Supply Relative Humidity %":49.7249984741,"b1eBcHjc Return Air Temperature":74.7750015259,"type":"AHU","subType":"","Status":true},"2020-04-19T20:00:00.000Z":{"dymclFPd Zone Temperature":71.9000015259,"ygZXCNrx Humidifier Valve %":0,"dECNkkkx Duct Static Pressure":0.5,"JJTf4KIN Mixed Air Temperature":68.0,"ejzJNJVA TvG2WGjE Flow Setpoint":750,"QaxazYRs Pre Heating Temp":66.3499984741,"ymhl1rIT Static Pressure Setpoint":0.5,"7J5Znp6z Preheat Valve %":0,"m99GC7uz Supply Fan Output %":12.4941596985,"3p3Wd2Zp Cooling Valve %":0,"nqWMaKsU hq1bHbcu Flow":1.3410240412,"iAtum58lYXB6Es Zone Relative Humidity %":40.0750007629,"AqlRfdQi Power (Calc)":0.0312901059,"9tAKv3tG Setpoint Temperature":58,"L4Vb3H0J Schedule":0.0,"Kamr4cZz Supply Air Temperature":63.375,"QNupgV5D Supply Relative Humidity Setpoint %":30,"OratacDL Supply Relative Humidity %":49.625,"b1eBcHjc Return Air Temperature":74.9000015259,"type":"AHU","subType":"","Status":true},"2020-04-19T20:15:00.000Z":{"dymclFPd Zone Temperature":71.9499969482,"ygZXCNrx Humidifier Valve %":0,"dECNkkkx Duct Static Pressure":0.5,"JJTf4KIN Mixed Air Temperature":68.9749984741,"ejzJNJVA TvG2WGjE Flow Setpoint":750,"QaxazYRs Pre Heating Temp":66.6500015259,"ymhl1rIT Static Pressure Setpoint":0.5,"7J5Znp6z Preheat Valve %":0,"m99GC7uz Supply Fan Output %":12.5636081696,"3p3Wd2Zp Cooling Valve %":0,"nqWMaKsU hq1bHbcu Flow":1.3655691147,"iAtum58lYXB6Es Zone Relative Humidity %":40.2750015259,"AqlRfdQi Power (Calc)":0.0318147873,"9tAKv3tG Setpoint Temperature":58,"L4Vb3H0J Schedule":0.0,"Kamr4cZz Supply Air Temperature":63.4749984741,"QNupgV5D Supply Relative Humidity Setpoint %":30,"OratacDL Supply Relative Humidity %":49.4749984741,"b1eBcHjc Return Air Temperature":74.9749984741,"type":"AHU","subType":"","Status":true},"2020-04-19T20:30:00.000Z":{"dymclFPd Zone Temperature":71.9749984741,"ygZXCNrx Humidifier Valve %":0,"dECNkkkx Duct Static Pressure":0.5,"JJTf4KIN Mixed Air Temperature":66.875,"ejzJNJVA TvG2WGjE Flow Setpoint":750,"QaxazYRs Pre Heating Temp":65.8000030518,"ymhl1rIT Static Pressure Setpoint":0.5,"7J5Znp6z Preheat Valve %":0,"m99GC7uz Supply Fan Output %":12.5682516098,"3p3Wd2Zp Cooling Valve %":0,"nqWMaKsU hq1bHbcu Flow":1.3870817423,"iAtum58lYXB6Es Zone Relative Humidity %":40.2249984741,"AqlRfdQi Power (Calc)":0.0318500761,"9tAKv3tG Setpoint Temperature":58,"L4Vb3H0J Schedule":0.0,"Kamr4cZz Supply Air Temperature":63.5499992371,"QNupgV5D Supply Relative Humidity Setpoint %":30,"OratacDL Supply Relative Humidity %":49.5,"b1eBcHjc Return Air Temperature":75.0,"type":"AHU","subType":"","Status":true}}